{"data": [{"image_url": "test_wave/superquadric_1/scale=0.250_distortion=25.000_scene=8", "frame_idx": 31, "probe_touching": false, "probe_location": [178, 285], "gt_bounding_box": [], "mask_idx": 0, "mask_val": 0, "obj_shape_data": [1.6410796875428095, 3.899918971327343, 1.7844087362168104], "obj_scaling_data": [4.0, 4.0, 4.0, 8.0], "obj_shape_type": "superellipsoid", "obj_location_data": [-0.23080711335220572, -11.01255067945227, 7.806695568395155], "obj_rotation_data": [0.024930691738073035, -0.5560258091205313, 0.7681260670696803, 0.3165376838377773], "obj_texture_data": {"type": "wave", "params": {"Scale": 0.25, "Distortion": 25.0, "Detail": 0.864054557322155, "Detail Scale": 0.7818689498405675, "Detail Roughness": 0.6064474267365507}}, "background_texture": {"type": "wave", "params": {"Scale": 0.25, "Distortion": 25.0, "Detail": 1.0891829836618743, "Detail Scale": 0.6098765566972639, "Detail Roughness": 0.7068196115949519}}}, {"image_url": "test_wave/superquadric_1/scale=0.250_distortion=37.500_scene=8", "frame_idx": 62, "probe_touching": true, "probe_location": [238, 243], "gt_bounding_box": [[176, 147], [312, 303]], "mask_idx": 0, "mask_val": 40, "obj_shape_data": [0.5418142275541812, 1.3064723077211902, 2.522003288863059], "obj_scaling_data": [4.0, 4.0, 4.0, 8.0], "obj_shape_type": "superellipsoid", "obj_location_data": [-1.2456674165579433, -0.5534226546374198, 1.044692891599803], "obj_rotation_data": [-0.9987569212189223, 0.04866650448888724, -0.004466342602471415, 0.009809966457118633], "obj_texture_data": {"type": "wave", "params": {"Scale": 0.25, "Distortion": 37.5, "Detail": 0.09350939242211598, "Detail Scale": 0.7364142088742958, "Detail Roughness": 0.6055396328911633}}, "background_texture": {"type": "wave", "params": {"Scale": 0.25, "Distortion": 37.5, "Detail": 1.3674159283012663, "Detail Scale": 0.7634947086863814, "Detail Roughness": 0.5023074293022896}}}, {"image_url": "test_wave/superquadric_1/scale=0.250_distortion=50.000_scene=8", "frame_idx": 18, "probe_touching": false, "probe_location": [238, 64], "gt_bounding_box": [], "mask_idx": 0, "mask_val": 0, "obj_shape_data": [1.059250795883389, 3.0053091940843175, 0.01855759510819222], "obj_scaling_data": [4.0, 4.0, 4.0, 8.0], "obj_shape_type": "supertoroid", "obj_location_data": [10.302265616906267, -8.812764283627295, -3.283521109872762], "obj_rotation_data": [0.6234898018587336, 0.0012116545727649493, 0.6349820552772838, 0.4561324241349106], "obj_texture_data": {"type": "wave", "params": {"Scale": 0.25, "Distortion": 50.0, "Detail": 1.734485889892946, "Detail Scale": 0.7885000364917085, "Detail Roughness": 0.3004551343241591}}, "background_texture": {"type": "wave", "params": {"Scale": 0.25, "Distortion": 50.0, "Detail": 0.6945283730127587, "Detail Scale": 0.5148609580025125, "Detail Roughness": 0.4048552395649296}}}, {"image_url": "test_wave/superquadric_1/scale=0.500_distortion=25.000_scene=8", "frame_idx": 14, "probe_touching": true, "probe_location": [224, 283], "gt_bounding_box": [[185, 259], [265, 351]], "mask_idx": 0, "mask_val": 40, "obj_shape_data": [3.8205192724077084, 1.2228492988059638, 2.3635374641911424], "obj_scaling_data": [4.0, 4.0, 4.0, 8.0], "obj_shape_type": "superellipsoid", "obj_location_data": [-8.93461613816083, 5.422157195382517, -8.9676303656521], "obj_rotation_data": [0.766044443118978, -0.21079281962282098, 0.4614258094940795, -0.39475121367100197], "obj_texture_data": {"type": "wave", "params": {"Scale": 0.5, "Distortion": 25.0, "Detail": 0.15625293951639918, "Detail Scale": 0.846484938778973, "Detail Roughness": 0.41055569518570983}}, "background_texture": {"type": "wave", "params": {"Scale": 0.5, "Distortion": 25.0, "Detail": 1.749033834844239, "Detail Scale": 0.7385206911797517, "Detail Roughness": 0.44270758799440746}}}, {"image_url": "test_wave/superquadric_1/scale=0.500_distortion=37.500_scene=8", "frame_idx": 52, "probe_touching": false, "probe_location": [367, 332], "gt_bounding_box": [], "mask_idx": 0, "mask_val": 0, "obj_shape_data": [3.5005468798001966, 1.3702428019507993, 1.452578736041105], "obj_scaling_data": [4.0, 4.0, 4.0, 8.0], "obj_shape_type": "superellipsoid", "obj_location_data": [-8.162536576263395, 11.781921169222109, -1.9589072912091123], "obj_rotation_data": [-0.8532908816321556, -0.4413661421490396, 0.22158741851397776, 0.16730097382921483], "obj_texture_data": {"type": "wave", "params": {"Scale": 0.5, "Distortion": 37.5, "Detail": 1.7189729396301086, "Detail Scale": 0.6141518736036284, "Detail Roughness": 0.7164625742668582}}, "background_texture": {"type": "wave", "params": {"Scale": 0.5, "Distortion": 37.5, "Detail": 1.4681132643903774, "Detail Scale": 0.8006391844411818, "Detail Roughness": 0.2628621368475848}}}, {"image_url": "test_wave/superquadric_1/scale=0.500_distortion=50.000_scene=8", "frame_idx": 1, "probe_touching": true, "probe_location": [25, 254], "gt_bounding_box": [[0, 232], [28, 276]], "mask_idx": 0, "mask_val": 40, "obj_shape_data": [2.482106140895759, 0.34152384332394553, 1.6647499330883617], "obj_scaling_data": [4.0, 4.0, 4.0, 8.0], "obj_shape_type": "superellipsoid", "obj_location_data": [-10.15104187937224, -14.373517433189944, -1.3266360818864744], "obj_rotation_data": [0.9987569212189223, 0.029201906681785607, 0.017534209295451852, -0.036392478176552764], "obj_texture_data": {"type": "wave", "params": {"Scale": 0.5, "Distortion": 50.0, "Detail": 0.21629484266287302, "Detail Scale": 0.887118948748745, "Detail Roughness": 0.6600637089103982}}, "background_texture": {"type": "wave", "params": {"Scale": 0.5, "Distortion": 50.0, "Detail": 0.25759206533398604, "Detail Scale": 0.727973760703595, "Detail Roughness": 0.7312613283496012}}}, {"image_url": "test_wave/superquadric_1/scale=0.750_distortion=25.000_scene=8", "frame_idx": 46, "probe_touching": false, "probe_location": [453, 457], "gt_bounding_box": [], "mask_idx": 0, "mask_val": 0, "obj_shape_data": [1.8693365700180369, 1.2880911696801753, 0.21114172733912664], "obj_scaling_data": [4.0, 4.0, 4.0, 8.0], "obj_shape_type": "supertoroid", "obj_location_data": [6.28640335777855, 6.5841536764045, 1.9171960685431968], "obj_rotation_data": [-0.6616858375968595, 0.36713994277615314, 0.6536962032767885, 0.00783508542245403], "obj_texture_data": {"type": "wave", "params": {"Scale": 0.75, "Distortion": 25.0, "Detail": 0.8290101132373111, "Detail Scale": 0.9553300710255461, "Detail Roughness": 0.5787000473967843}}, "background_texture": {"type": "wave", "params": {"Scale": 0.75, "Distortion": 25.0, "Detail": 0.7752164900459533, "Detail Scale": 0.6400513662855866, "Detail Roughness": 0.4094660852725947}}}, {"image_url": "test_wave/superquadric_1/scale=0.750_distortion=37.500_scene=8", "frame_idx": 8, "probe_touching": true, "probe_location": [257, 239], "gt_bounding_box": [[185, 157], [306, 286]], "mask_idx": 0, "mask_val": 40, "obj_shape_data": [2.2735674019144425, 2.7958233897005798, 0.7528336339460899], "obj_scaling_data": [4.0, 4.0, 4.0, 8.0], "obj_shape_type": "superellipsoid", "obj_location_data": [1.964914129991525, -3.739180792913611, 3.0519275946515063], "obj_rotation_data": [0.9214762118704076, 0.3037762187319614, -0.1977288343311444, 0.13965997266189734], "obj_texture_data": {"type": "wave", "params": {"Scale": 0.75, "Distortion": 37.5, "Detail": 1.9533463109907894, "Detail Scale": 0.8905042305715543, "Detail Roughness": 0.3925820593051325}}, "background_texture": {"type": "wave", "params": {"Scale": 0.75, "Distortion": 37.5, "Detail": 0.003785249492847864, "Detail Scale": 0.9218714304063227, "Detail Roughness": 0.4759297555448437}}}, {"image_url": "test_wave/superquadric_1/scale=0.750_distortion=50.000_scene=8", "frame_idx": 34, "probe_touching": false, "probe_location": [293, 261], "gt_bounding_box": [], "mask_idx": 0, "mask_val": 0, "obj_shape_data": [3.4272965368847235, 3.88291744708453, 3.148681663362245], "obj_scaling_data": [4.0, 4.0, 4.0, 8.0], "obj_shape_type": "supertoroid", "obj_location_data": [-6.182342464223767, -1.277386848535977, 13.641870641301438], "obj_rotation_data": [-0.12434370464748494, 0.7374163603914695, 0.2518729673467377, 0.6142603380175922], "obj_texture_data": {"type": "wave", "params": {"Scale": 0.75, "Distortion": 50.0, "Detail": 1.2965228978992995, "Detail Scale": 0.5469929268432212, "Detail Roughness": 0.5444846672982433}}, "background_texture": {"type": "wave", "params": {"Scale": 0.75, "Distortion": 50.0, "Detail": 1.5827661141082519, "Detail Scale": 0.7675707653347568, "Detail Roughness": 0.5982794091186652}}}, {"image_url": "test_wave/superquadric_2/scale=0.250_distortion=25.000_scene=8", "frame_idx": 12, "probe_touching": true, "probe_location": [321, 364], "gt_bounding_box": [[206, 289], [342, 423]], "mask_idx": 0, "mask_val": 40, "obj_shape_data": [0.8246277660956896, 0.7764660010938045, 1.2370208628679435], "obj_scaling_data": [3.5, 3.5, 3.5, 7.0], "obj_shape_type": "superellipsoid", "obj_location_data": [2.6176608498383587, -2.362340181434507, -4.9687290585336585], "obj_rotation_data": [0.8262387743159949, -0.012306585430199116, 0.5536149977299911, -0.10338505723881773], "obj_texture_data": {"type": "wave", "params": {"Scale": 0.25, "Distortion": 25.0, "Detail": 0.15518554896684034, "Detail Scale": 0.8622161767999237, "Detail Roughness": 0.7053669222490423}}, "background_texture": {"type": "wave", "params": {"Scale": 0.25, "Distortion": 25.0, "Detail": 1.7372912630657364, "Detail Scale": 0.6194562437734292, "Detail Roughness": 0.34256247631602205}}}, {"image_url": "test_wave/superquadric_2/scale=0.250_distortion=37.500_scene=8", "frame_idx": 32, "probe_touching": false, "probe_location": [382, 335], "gt_bounding_box": [], "mask_idx": 0, "mask_val": 0, "obj_shape_data": [1.4291895624074304, 1.843250621647102, 0.9433703986094978], "obj_scaling_data": [3.5, 3.5, 3.5, 7.0], "obj_shape_type": "supertoroid", "obj_location_data": [-7.994963257353248, -1.794017160312071, -4.283936602376935], "obj_rotation_data": [-0.02493069173807269, -0.6055421710366834, -0.48226225013481344, 0.6325506001898568], "obj_texture_data": {"type": "wave", "params": {"Scale": 0.25, "Distortion": 37.5, "Detail": 1.9591193867006031, "Detail Scale": 0.9680110199294204, "Detail Roughness": 0.6932094495324965}}, "background_texture": {"type": "wave", "params": {"Scale": 0.25, "Distortion": 37.5, "Detail": 1.5046082276458097, "Detail Scale": 0.5895190531418544, "Detail Roughness": 0.5080745028626886}}}, {"image_url": "test_wave/superquadric_2/scale=0.250_distortion=50.000_scene=8", "frame_idx": 50, "probe_touching": true, "probe_location": [357, 344], "gt_bounding_box": [[303, 77], [511, 423]], "mask_idx": 0, "mask_val": 60, "obj_shape_data": [0.47045144055611343, 0.8794273720176693, 2.6705784325712063], "obj_scaling_data": [3.5, 3.5, 3.5, 7.0], "obj_shape_type": "superellipsoid", "obj_location_data": [6.786554873517551, 15.812640769483004, 2.4537291088760913], "obj_rotation_data": [-0.7971325072229225, 0.45654896686813357, -0.3574705948808902, 0.1683970919453178], "obj_texture_data": {"type": "wave", "params": {"Scale": 0.25, "Distortion": 50.0, "Detail": 1.8618572695425804, "Detail Scale": 0.8464223368954168, "Detail Roughness": 0.7241469220419487}}, "background_texture": {"type": "wave", "params": {"Scale": 0.25, "Distortion": 50.0, "Detail": 0.32029460498448414, "Detail Scale": 0.9649111854183952, "Detail Roughness": 0.676192699869862}}}, {"image_url": "test_wave/superquadric_2/scale=0.500_distortion=25.000_scene=8", "frame_idx": 36, "probe_touching": false, "probe_location": [447, 367], "gt_bounding_box": [], "mask_idx": 0, "mask_val": 0, "obj_shape_data": [0.06314586673752517, 3.6168843556756882, 2.244667348756706], "obj_scaling_data": [3.5, 3.5, 3.5, 7.0], "obj_shape_type": "superellipsoid", "obj_location_data": [1.5962221786130486, -3.8231430997818068, 2.4107577459343994], "obj_rotation_data": [-0.22252093395631434, 0.3618520255817943, 0.527565568585667, -0.7356779977520356], "obj_texture_data": {"type": "wave", "params": {"Scale": 0.5, "Distortion": 25.0, "Detail": 0.45353370100903434, "Detail Scale": 0.7432338871118032, "Detail Roughness": 0.4860155824467376}}, "background_texture": {"type": "wave", "params": {"Scale": 0.5, "Distortion": 25.0, "Detail": 1.3113311108894152, "Detail Scale": 0.8030592386574191, "Detail Roughness": 0.6193120927057347}}}, {"image_url": "test_wave/superquadric_2/scale=0.500_distortion=37.500_scene=8", "frame_idx": 1, "probe_touching": true, "probe_location": [110, 177], "gt_bounding_box": [[0, 0], [340, 238]], "mask_idx": 1, "mask_val": 60, "obj_shape_data": [0.16536898623037447, 3.4446166171905004, 2.8649714986229986], "obj_scaling_data": [3.5, 3.5, 3.5, 7.0], "obj_shape_type": "supertoroid", "obj_location_data": [-1.3607492267989838, -7.799803531074447, 8.851796218156533], "obj_rotation_data": [0.9987569212189223, 0.025953997991543756, -0.025700429312084376, 0.0339188773211731], "obj_texture_data": {"type": "wave", "params": {"Scale": 0.5, "Distortion": 37.5, "Detail": 0.5517207467836465, "Detail Scale": 0.9505847487734613, "Detail Roughness": 0.4627473174905982}}, "background_texture": {"type": "wave", "params": {"Scale": 0.5, "Distortion": 37.5, "Detail": 1.5245208923967406, "Detail Scale": 0.5324442853774887, "Detail Roughness": 0.6585226568700085}}}, {"image_url": "test_wave/superquadric_2/scale=0.500_distortion=50.000_scene=8", "frame_idx": 39, "probe_touching": false, "probe_location": [154, 424], "gt_bounding_box": [], "mask_idx": 0, "mask_val": 0, "obj_shape_data": [0.052552083071688314, 2.3096309915527713, 2.9267965253347574], "obj_scaling_data": [3.5, 3.5, 3.5, 7.0], "obj_shape_type": "superellipsoid", "obj_location_data": [3.7279930879973113, -6.546959931052553, 11.27173580851792], "obj_rotation_data": [-0.3653410243663951, -0.2421624400612404, 0.4784912544473434, -0.7608741078233027], "obj_texture_data": {"type": "wave", "params": {"Scale": 0.5, "Distortion": 50.0, "Detail": 1.4149175575990374, "Detail Scale": 0.8921218928097183, "Detail Roughness": 0.5316605803208436}}, "background_texture": {"type": "wave", "params": {"Scale": 0.5, "Distortion": 50.0, "Detail": 0.5770434454558042, "Detail Scale": 0.8734057953868719, "Detail Roughness": 0.7474263656274521}}}, {"image_url": "test_wave/superquadric_2/scale=0.750_distortion=25.000_scene=8", "frame_idx": 32, "probe_touching": true, "probe_location": [333, 91], "gt_bounding_box": [[95, 34], [420, 322]], "mask_idx": 0, "mask_val": 40, "obj_shape_data": [3.240320711247088, 0.9526529432942435, 3.304575143639447], "obj_scaling_data": [3.5, 3.5, 3.5, 7.0], "obj_shape_type": "supertoroid", "obj_location_data": [-3.9726780469380154, 3.5641034611350766, 0.0183833926645048], "obj_rotation_data": [-0.02493069173807269, 0.5393310460927812, -0.5605477348106973, -0.6279225432555545], "obj_texture_data": {"type": "wave", "params": {"Scale": 0.75, "Distortion": 25.0, "Detail": 1.9219149173310917, "Detail Scale": 0.6543861239093308, "Detail Roughness": 0.6288277920495624}}, "background_texture": {"type": "wave", "params": {"Scale": 0.75, "Distortion": 25.0, "Detail": 0.04607700098682921, "Detail Scale": 0.5011999807637737, "Detail Roughness": 0.3895140314238325}}}, {"image_url": "test_wave/superquadric_2/scale=0.750_distortion=37.500_scene=8", "frame_idx": 45, "probe_touching": false, "probe_location": [373, 93], "gt_bounding_box": [], "mask_idx": 0, "mask_val": 0, "obj_shape_data": [1.7143631710023552, 3.8091151801096292, 0.7093872682750587], "obj_scaling_data": [3.5, 3.5, 3.5, 7.0], "obj_shape_type": "supertoroid", "obj_location_data": [-17.51396730493527, -1.7782613817710577, 9.650964224447112], "obj_rotation_data": [-0.6234898018587335, 0.6103647068225964, 0.4253544366105568, 0.24039341692159402], "obj_texture_data": {"type": "wave", "params": {"Scale": 0.75, "Distortion": 37.5, "Detail": 0.034485604293950756, "Detail Scale": 0.5919086103931803, "Detail Roughness": 0.30309879542357127}}, "background_texture": {"type": "wave", "params": {"Scale": 0.75, "Distortion": 37.5, "Detail": 0.6057925566079017, "Detail Scale": 0.8141865976252096, "Detail Roughness": 0.6399462338821135}}}, {"image_url": "test_wave/superquadric_2/scale=0.750_distortion=50.000_scene=8", "frame_idx": 2, "probe_touching": true, "probe_location": [114, 255], "gt_bounding_box": [[0, 108], [240, 323]], "mask_idx": 1, "mask_val": 60, "obj_shape_data": [2.758326918878826, 1.7298729462776616, 0.2193216158250184], "obj_scaling_data": [3.5, 3.5, 3.5, 7.0], "obj_shape_type": "supertoroid", "obj_location_data": [-5.787157809458466, -7.760198885692289, 2.5545395093627414], "obj_rotation_data": [0.9950307753654014, -0.027760287751973107, 0.0917821102112937, -0.026817284441525154], "obj_texture_data": {"type": "wave", "params": {"Scale": 0.75, "Distortion": 50.0, "Detail": 0.5618414094979718, "Detail Scale": 0.9734392062372517, "Detail Roughness": 0.3449469031735714}}, "background_texture": {"type": "wave", "params": {"Scale": 0.75, "Distortion": 50.0, "Detail": 0.9953309103942096, "Detail Scale": 0.9417159125914194, "Detail Roughness": 0.7221888844659907}}}, {"image_url": "test_wave/superquadric_3/scale=0.250_distortion=25.000_scene=8", "frame_idx": 22, "probe_touching": false, "probe_location": [80, 246], "gt_bounding_box": [], "mask_idx": 0, "mask_val": 0, "obj_shape_data": [1.1469203384675162, 0.45276401005092975, 2.558338966609317], "obj_scaling_data": [3.0, 3.0, 3.0, 6.0], "obj_shape_type": "superellipsoid", "obj_location_data": [-4.842233001582395, -2.5494320837658084, -2.4928838117092846], "obj_rotation_data": [0.4562106573531629, -0.4628107008020874, 0.048659089280385655, 0.7584921781870128], "obj_texture_data": {"type": "wave", "params": {"Scale": 0.25, "Distortion": 25.0, "Detail": 1.7367765778387192, "Detail Scale": 0.9974322646496878, "Detail Roughness": 0.5689697810188168}}, "background_texture": {"type": "wave", "params": {"Scale": 0.25, "Distortion": 25.0, "Detail": 1.253622764116227, "Detail Scale": 0.8121070444641686, "Detail Roughness": 0.3766155936416381}}}, {"image_url": "test_wave/superquadric_3/scale=0.250_distortion=37.500_scene=8", "frame_idx": 6, "probe_touching": true, "probe_location": [371, 301], "gt_bounding_box": [[329, 257], [451, 370]], "mask_idx": 1, "mask_val": 60, "obj_shape_data": [1.9137314408662027, 0.8229258642524149, 1.6572094389064744], "obj_scaling_data": [3.0, 3.0, 3.0, 6.0], "obj_shape_type": "superellipsoid", "obj_location_data": [6.66798074724495, 2.544104729150273, -2.7616054765473868], "obj_rotation_data": [0.9555728057861408, -0.17210678136974356, -0.16126501193452655, 0.17678649432099394], "obj_texture_data": {"type": "wave", "params": {"Scale": 0.25, "Distortion": 37.5, "Detail": 1.6218085361590433, "Detail Scale": 0.6677301427537472, "Detail Roughness": 0.25985800747505833}}, "background_texture": {"type": "wave", "params": {"Scale": 0.25, "Distortion": 37.5, "Detail": 0.07533698319479276, "Detail Scale": 0.6023000903350053, "Detail Roughness": 0.35951536357439345}}}, {"image_url": "test_wave/superquadric_3/scale=0.250_distortion=50.000_scene=8", "frame_idx": 29, "probe_touching": false, "probe_location": [160, 373], "gt_bounding_box": [], "mask_idx": 0, "mask_val": 0, "obj_shape_data": [2.5129502640095978, 3.146102516646053, 3.199986295316471], "obj_scaling_data": [3.0, 3.0, 3.0, 6.0], "obj_shape_type": "superellipsoid", "obj_location_data": [2.942547103034985, 10.406050517992096, -12.071653455790527], "obj_rotation_data": [0.12434370464748506, 0.7963063392266339, -0.1680015950379262, 0.5676357293958239], "obj_texture_data": {"type": "wave", "params": {"Scale": 0.25, "Distortion": 50.0, "Detail": 0.08605479808440775, "Detail Scale": 0.8100815556771089, "Detail Roughness": 0.325950628299776}}, "background_texture": {"type": "wave", "params": {"Scale": 0.25, "Distortion": 50.0, "Detail": 1.817018562847929, "Detail Scale": 0.9022768004057569, "Detail Roughness": 0.7011282385754407}}}, {"image_url": "test_wave/superquadric_3/scale=0.500_distortion=25.000_scene=8", "frame_idx": 50, "probe_touching": true, "probe_location": [371, 352], "gt_bounding_box": [[145, 222], [411, 511]], "mask_idx": 1, "mask_val": 60, "obj_shape_data": [3.620099333499136, 2.4284749749769055, 2.0265813101402212], "obj_scaling_data": [3.0, 3.0, 3.0, 6.0], "obj_shape_type": "supertoroid", "obj_location_data": [2.9892938435588445, 0.09930270253391049, -6.517882584919867], "obj_rotation_data": [-0.7971325072229225, -0.2587474478915185, -0.26875347545081907, -0.4747642505193808], "obj_texture_data": {"type": "wave", "params": {"Scale": 0.5, "Distortion": 25.0, "Detail": 0.9789348033584762, "Detail Scale": 0.9682373073240614, "Detail Roughness": 0.5669227264557319}}, "background_texture": {"type": "wave", "params": {"Scale": 0.5, "Distortion": 25.0, "Detail": 1.4931948091881548, "Detail Scale": 0.5901275644386266, "Detail Roughness": 0.3314764645140505}}}, {"image_url": "test_wave/superquadric_3/scale=0.500_distortion=37.500_scene=8", "frame_idx": 12, "probe_touching": false, "probe_location": [226, 89], "gt_bounding_box": [], "mask_idx": 0, "mask_val": 0, "obj_shape_data": [2.8703563939773504, 2.4159093174731017, 1.6416514279651262], "obj_scaling_data": [3.0, 3.0, 3.0, 6.0], "obj_shape_type": "superellipsoid", "obj_location_data": [-0.26843191507799496, -13.076306914111232, 3.444659760508041], "obj_rotation_data": [0.8262387743159949, 0.3115969591168292, 0.06632466961628258, -0.4645835351002427], "obj_texture_data": {"type": "wave", "params": {"Scale": 0.5, "Distortion": 37.5, "Detail": 1.4865034881572765, "Detail Scale": 0.5846901476355324, "Detail Roughness": 0.39580909154749755}}, "background_texture": {"type": "wave", "params": {"Scale": 0.5, "Distortion": 37.5, "Detail": 1.3542107178069829, "Detail Scale": 0.8721915641308615, "Detail Roughness": 0.3966869887818571}}}, {"image_url": "test_wave/superquadric_3/scale=0.500_distortion=50.000_scene=8", "frame_idx": 35, "probe_touching": true, "probe_location": [267, 112], "gt_bounding_box": [[245, 0], [511, 275]], "mask_idx": 2, "mask_val": 80, "obj_shape_data": [0.4579900360999234, 3.456018228850241, 0.3485788019013282], "obj_scaling_data": [3.0, 3.0, 3.0, 6.0], "obj_shape_type": "supertoroid", "obj_location_data": [10.50099905471145, 0.4926919473658765, 6.871679679621024], "obj_rotation_data": [-0.1736481776669303, -0.7861238772863214, -0.5595876285430451, 0.1967669838536075], "obj_texture_data": {"type": "wave", "params": {"Scale": 0.5, "Distortion": 50.0, "Detail": 1.8909739841049062, "Detail Scale": 0.7613230713666889, "Detail Roughness": 0.42852001211775304}}, "background_texture": {"type": "wave", "params": {"Scale": 0.5, "Distortion": 50.0, "Detail": 1.6461852247754345, "Detail Scale": 0.6497804803366531, "Detail Roughness": 0.6198291831128375}}}, {"image_url": "test_wave/superquadric_3/scale=0.750_distortion=25.000_scene=8", "frame_idx": 18, "probe_touching": false, "probe_location": [451, 100], "gt_bounding_box": [], "mask_idx": 0, "mask_val": 0, "obj_shape_data": [3.7485431586497455, 1.3826296737014865, 3.039412592215354], "obj_scaling_data": [3.0, 3.0, 3.0, 6.0], "obj_shape_type": "superellipsoid", "obj_location_data": [-2.7166454856174673, 7.528257430925045, 4.578805496164531], "obj_rotation_data": [0.6234898018587336, 0.6128240144165176, 0.3984651273260407, -0.2773675118639946], "obj_texture_data": {"type": "wave", "params": {"Scale": 0.75, "Distortion": 25.0, "Detail": 1.7350496468970968, "Detail Scale": 0.6313785003774407, "Detail Roughness": 0.5208343973432148}}, "background_texture": {"type": "wave", "params": {"Scale": 0.75, "Distortion": 25.0, "Detail": 0.20032469848968248, "Detail Scale": 0.9169230504114758, "Detail Roughness": 0.3173107310940662}}}, {"image_url": "test_wave/superquadric_3/scale=0.750_distortion=37.500_scene=8", "frame_idx": 20, "probe_touching": true, "probe_location": [347, 369], "gt_bounding_box": [[284, 315], [420, 434]], "mask_idx": 0, "mask_val": 40, "obj_shape_data": [3.7909160624920406, 3.854523505931939, 0.29202912632946304], "obj_scaling_data": [3.0, 3.0, 3.0, 6.0], "obj_shape_type": "superellipsoid", "obj_location_data": [9.24843124736057, -4.207918393231203, -1.7644737877494499], "obj_rotation_data": [0.5425462638657593, 0.4842335465329811, 0.6608041628373853, -0.18573982436241138], "obj_texture_data": {"type": "wave", "params": {"Scale": 0.75, "Distortion": 37.5, "Detail": 1.8557979536030726, "Detail Scale": 0.9952473014174834, "Detail Roughness": 0.6957054457602228}}, "background_texture": {"type": "wave", "params": {"Scale": 0.75, "Distortion": 37.5, "Detail": 1.2296097553898253, "Detail Scale": 0.7127149464862782, "Detail Roughness": 0.6677666906990146}}}, {"image_url": "test_wave/superquadric_3/scale=0.750_distortion=50.000_scene=8", "frame_idx": 29, "probe_touching": false, "probe_location": [445, 343], "gt_bounding_box": [], "mask_idx": 0, "mask_val": 0, "obj_shape_data": [3.4397434656773505, 0.8781131713486668, 2.399361163397144], "obj_scaling_data": [3.0, 3.0, 3.0, 6.0], "obj_shape_type": "superellipsoid", "obj_location_data": [0.6440558996638708, -8.124594530554528, -10.016124933920421], "obj_rotation_data": [0.12434370464748506, -0.08820136829526627, 0.5509744378808087, -0.8204793297501825], "obj_texture_data": {"type": "wave", "params": {"Scale": 0.75, "Distortion": 50.0, "Detail": 1.5243571032152805, "Detail Scale": 0.667076934674891, "Detail Roughness": 0.273081034129778}}, "background_texture": {"type": "wave", "params": {"Scale": 0.75, "Distortion": 50.0, "Detail": 1.5952488613983518, "Detail Scale": 0.5571088428300501, "Detail Roughness": 0.46376763048264685}}}, {"image_url": "test_wave/superquadric_4/scale=0.250_distortion=25.000_scene=8", "frame_idx": 32, "probe_touching": true, "probe_location": [190, 80], "gt_bounding_box": [[126, 0], [304, 116]], "mask_idx": 1, "mask_val": 60, "obj_shape_data": [1.482138772397556, 0.9493923963755644, 1.7963506366774424], "obj_scaling_data": [2.0, 2.0, 2.0, 4.0], "obj_shape_type": "supertoroid", "obj_location_data": [-4.871169170380148, 2.7598666994743315, 11.899646905786003], "obj_rotation_data": [-0.02493069173807269, -0.6172210638845003, -0.009608211257478775, 0.7863359976391635], "obj_texture_data": {"type": "wave", "params": {"Scale": 0.25, "Distortion": 25.0, "Detail": 0.7369463250832955, "Detail Scale": 0.9583934239052966, "Detail Roughness": 0.3855628609643821}}, "background_texture": {"type": "wave", "params": {"Scale": 0.25, "Distortion": 25.0, "Detail": 0.47319014843157703, "Detail Scale": 0.5214293577074874, "Detail Roughness": 0.36729240099924715}}}, {"image_url": "test_wave/superquadric_4/scale=0.250_distortion=37.500_scene=8", "frame_idx": 59, "probe_touching": false, "probe_location": [175, 263], "gt_bounding_box": [], "mask_idx": 0, "mask_val": 0, "obj_shape_data": [0.6907563937621427, 0.44560985118772795, 1.7853916516664836], "obj_scaling_data": [2.0, 2.0, 2.0, 4.0], "obj_shape_type": "supertoroid", "obj_location_data": [-12.048027172174683, -2.157568729139612, 3.7739275386065376], "obj_rotation_data": [-0.9801724878485439, -0.1248557395070358, -0.07704256323705053, 0.13318176236561932], "obj_texture_data": {"type": "wave", "params": {"Scale": 0.25, "Distortion": 37.5, "Detail": 1.2775132462176624, "Detail Scale": 0.8063671839773876, "Detail Roughness": 0.5691397761328315}}, "background_texture": {"type": "wave", "params": {"Scale": 0.25, "Distortion": 37.5, "Detail": 1.6109094212376747, "Detail Scale": 0.5190456263427773, "Detail Roughness": 0.4829737127863142}}}, {"image_url": "test_wave/superquadric_4/scale=0.250_distortion=50.000_scene=8", "frame_idx": 31, "probe_touching": true, "probe_location": [207, 131], "gt_bounding_box": [[161, 0], [275, 168]], "mask_idx": 3, "mask_val": 100, "obj_shape_data": [3.4707076688680507, 3.645250552986124, 1.26616100418815], "obj_scaling_data": [2.0, 2.0, 2.0, 4.0], "obj_shape_type": "supertoroid", "obj_location_data": [-0.8502045544457724, -1.4267431857313257, 8.962103512277036], "obj_rotation_data": [0.024930691738073035, 0.5382046157340984, 0.37686579925171065, -0.7534496808456036], "obj_texture_data": {"type": "wave", "params": {"Scale": 0.25, "Distortion": 50.0, "Detail": 1.7226586503757466, "Detail Scale": 0.5605763723717717, "Detail Roughness": 0.6744088029615547}}, "background_texture": {"type": "wave", "params": {"Scale": 0.25, "Distortion": 50.0, "Detail": 0.4876132829954287, "Detail Scale": 0.8328470636270019, "Detail Roughness": 0.4967110395578007}}}, {"image_url": "test_wave/superquadric_4/scale=0.500_distortion=25.000_scene=8", "frame_idx": 35, "probe_touching": false, "probe_location": [262, 377], "gt_bounding_box": [], "mask_idx": 0, "mask_val": 0, "obj_shape_data": [1.0906381865011585, 3.5793116681150345, 2.8873466416894367], "obj_scaling_data": [2.0, 2.0, 2.0, 4.0], "obj_shape_type": "superellipsoid", "obj_location_data": [-1.0422446470497577, 15.490955167552185, 3.464581337762411], "obj_rotation_data": [-0.1736481776669303, 0.15740141928222698, 0.6565959812782958, -0.7169050292542846], "obj_texture_data": {"type": "wave", "params": {"Scale": 0.5, "Distortion": 25.0, "Detail": 0.77391198496385, "Detail Scale": 0.5378686701988652, "Detail Roughness": 0.3190856477633204}}, "background_texture": {"type": "wave", "params": {"Scale": 0.5, "Distortion": 25.0, "Detail": 0.08210721719150516, "Detail Scale": 0.5403604122562843, "Detail Roughness": 0.7466697263192439}}}, {"image_url": "test_wave/superquadric_4/scale=0.500_distortion=37.500_scene=8", "frame_idx": 52, "probe_touching": true, "probe_location": [304, 422], "gt_bounding_box": [[207, 365], [400, 511]], "mask_idx": 0, "mask_val": 40, "obj_shape_data": [0.9944031172445901, 2.0591218884096234, 3.8705625130354733], "obj_scaling_data": [2.0, 2.0, 2.0, 4.0], "obj_shape_type": "supertoroid", "obj_location_data": [5.212590010571714, -2.6048355606670723, -8.800891579017458], "obj_rotation_data": [-0.8532908816321556, 0.29097094112365207, -0.16221303078291438, -0.40114525472608553], "obj_texture_data": {"type": "wave", "params": {"Scale": 0.5, "Distortion": 37.5, "Detail": 1.982617071696782, "Detail Scale": 0.5480343281174547, "Detail Roughness": 0.4481509199082523}}, "background_texture": {"type": "wave", "params": {"Scale": 0.5, "Distortion": 37.5, "Detail": 0.21258834161992812, "Detail Scale": 0.5076354047665005, "Detail Roughness": 0.591087529918168}}}, {"image_url": "test_wave/superquadric_4/scale=0.500_distortion=50.000_scene=8", "frame_idx": 45, "probe_touching": false, "probe_location": [340, 218], "gt_bounding_box": [], "mask_idx": 0, "mask_val": 0, "obj_shape_data": [0.623295042203079, 3.240952428860323, 0.5975510350941089], "obj_scaling_data": [2.0, 2.0, 2.0, 4.0], "obj_shape_type": "supertoroid", "obj_location_data": [2.9778841349395786, 2.3243551216805414, 17.773589873484447], "obj_rotation_data": [-0.6234898018587335, -0.7291279468131482, -0.2431155219262212, 0.14327507512732723], "obj_texture_data": {"type": "wave", "params": {"Scale": 0.5, "Distortion": 50.0, "Detail": 1.6030892815951583, "Detail Scale": 0.6525358162068714, "Detail Roughness": 0.39350965120948805}}, "background_texture": {"type": "wave", "params": {"Scale": 0.5, "Distortion": 50.0, "Detail": 1.0345514357204149, "Detail Scale": 0.8002499294453647, "Detail Roughness": 0.3462405252446047}}}, {"image_url": "test_wave/superquadric_4/scale=0.750_distortion=25.000_scene=8", "frame_idx": 29, "probe_touching": true, "probe_location": [266, 244], "gt_bounding_box": [[239, 224], [298, 295]], "mask_idx": 2, "mask_val": 80, "obj_shape_data": [3.513230074679836, 0.5005819386174872, 1.8168845886618101], "obj_scaling_data": [2.0, 2.0, 2.0, 4.0], "obj_shape_type": "superellipsoid", "obj_location_data": [0.28460266214426966, -0.13731068322702075, -0.799560969634696], "obj_rotation_data": [0.12434370464748506, 0.010518408501458769, 0.5888041826797468, -0.7985847736189132], "obj_texture_data": {"type": "wave", "params": {"Scale": 0.75, "Distortion": 25.0, "Detail": 0.21184678574428295, "Detail Scale": 0.5479486121923818, "Detail Roughness": 0.5772099638946375}}, "background_texture": {"type": "wave", "params": {"Scale": 0.75, "Distortion": 25.0, "Detail": 1.4853091797694753, "Detail Scale": 0.5444839871633019, "Detail Roughness": 0.6185649786019314}}}, {"image_url": "test_wave/superquadric_4/scale=0.750_distortion=37.500_scene=8", "frame_idx": 25, "probe_touching": false, "probe_location": [136, 293], "gt_bounding_box": [], "mask_idx": 0, "mask_val": 0, "obj_shape_data": [1.7710215804539675, 1.9692643989241247, 1.0083869395729057], "obj_scaling_data": [2.0, 2.0, 2.0, 4.0], "obj_shape_type": "supertoroid", "obj_location_data": [1.042887904408332, -7.098033705906518, -6.7470451615591935], "obj_rotation_data": [0.31848665025168443, 0.674101581175071, -0.6433155549867621, 0.17406438056306828], "obj_texture_data": {"type": "wave", "params": {"Scale": 0.75, "Distortion": 37.5, "Detail": 1.4013502270959357, "Detail Scale": 0.6651002647595075, "Detail Roughness": 0.694435301320909}}, "background_texture": {"type": "wave", "params": {"Scale": 0.75, "Distortion": 37.5, "Detail": 0.5306850253187045, "Detail Scale": 0.8746683189513547, "Detail Roughness": 0.40167780337306414}}}, {"image_url": "test_wave/superquadric_4/scale=0.750_distortion=50.000_scene=8", "frame_idx": 40, "probe_touching": true, "probe_location": [378, 416], "gt_bounding_box": [[277, 343], [408, 511]], "mask_idx": 2, "mask_val": 80, "obj_shape_data": [3.2448389957712003, 0.8048251440698598, 1.0320519324338613], "obj_scaling_data": [2.0, 2.0, 2.0, 4.0], "obj_shape_type": "supertoroid", "obj_location_data": [6.034650244775724, 0.3172471996172032, -12.371721971748006], "obj_rotation_data": [-0.4112871031306118, 0.49404340463732227, 0.659588833585064, -0.3894953192821283], "obj_texture_data": {"type": "wave", "params": {"Scale": 0.75, "Distortion": 50.0, "Detail": 0.4864582399516617, "Detail Scale": 0.6664463982700828, "Detail Roughness": 0.32918711595873285}}, "background_texture": {"type": "wave", "params": {"Scale": 0.75, "Distortion": 50.0, "Detail": 0.9019733852386653, "Detail Scale": 0.8553736746772673, "Detail Roughness": 0.5378136884116227}}}, {"image_url": "test_voronoi/superquadric_1/scale=0.200_distortion=0.700_scene=8", "frame_idx": 21, "probe_touching": false, "probe_location": [472, 80], "gt_bounding_box": [], "mask_idx": 0, "mask_val": 0, "obj_shape_data": [0.3905398998094979, 0.17247332236265514, 3.7511800518320317], "obj_scaling_data": [4.0, 4.0, 4.0, 8.0], "obj_shape_type": "supertoroid", "obj_location_data": [-11.194346198600252, -2.2520482059646607, 12.116921700953993], "obj_rotation_data": [0.5000000000000001, 0.6492739794144702, 0.14162883507493035, -0.5553238449144934], "obj_texture_data": {"type": "voronoi", "params": {"Scale": 0.2, "Randomness": 0.7}}, "background_texture": {"type": "voronoi", "params": {"Scale": 0.2, "Randomness": 0.7}}}, {"image_url": "test_voronoi/superquadric_1/scale=0.200_distortion=0.850_scene=8", "frame_idx": 17, "probe_touching": true, "probe_location": [228, 85], "gt_bounding_box": [[157, 0], [269, 124]], "mask_idx": 0, "mask_val": 40, "obj_shape_data": [3.0449943502408354, 0.45200266108718434, 2.5880058456782664], "obj_scaling_data": [4.0, 4.0, 4.0, 8.0], "obj_shape_type": "superellipsoid", "obj_location_data": [-9.200043276241852, 3.791101653463914, 9.86583642818584], "obj_rotation_data": [0.6616858375968595, 0.13671009314443996, 0.7357081437397364, 0.047071541202857614], "obj_texture_data": {"type": "voronoi", "params": {"Scale": 0.2, "Randomness": 0.85}}, "background_texture": {"type": "voronoi", "params": {"Scale": 0.2, "Randomness": 0.85}}}, {"image_url": "test_voronoi/superquadric_1/scale=0.200_distortion=1.000_scene=8", "frame_idx": 13, "probe_touching": false, "probe_location": [371, 72], "gt_bounding_box": [], "mask_idx": 0, "mask_val": 0, "obj_shape_data": [3.1190115842450505, 2.2144139569272103, 1.419711199896869], "obj_scaling_data": [4.0, 4.0, 4.0, 8.0], "obj_shape_type": "superellipsoid", "obj_location_data": [-4.326825930678508, -2.9662205176104544, 11.55891790476307], "obj_rotation_data": [0.7971325072229225, 0.2279640818792763, -0.43827237548081355, 0.34717354189488703], "obj_texture_data": {"type": "voronoi", "params": {"Scale": 0.2, "Randomness": 1.0}}, "background_texture": {"type": "voronoi", "params": {"Scale": 0.2, "Randomness": 1.0}}}, {"image_url": "test_voronoi/superquadric_1/scale=0.600_distortion=0.700_scene=8", "frame_idx": 12, "probe_touching": true, "probe_location": [383, 269], "gt_bounding_box": [[115, 209], [426, 511]], "mask_idx": 0, "mask_val": 40, "obj_shape_data": [2.8580363251533374, 1.1102623225210355, 2.722262042215823], "obj_scaling_data": [4.0, 4.0, 4.0, 8.0], "obj_shape_type": "supertoroid", "obj_location_data": [-0.20689780380985778, -1.242381414254741, -8.114034283949433], "obj_rotation_data": [0.8262387743159949, 0.3440988473876324, -0.2927321398462433, 0.33650165726834796], "obj_texture_data": {"type": "voronoi", "params": {"Scale": 0.6000000000000001, "Randomness": 0.7}}, "background_texture": {"type": "voronoi", "params": {"Scale": 0.6000000000000001, "Randomness": 0.7}}}, {"image_url": "test_voronoi/superquadric_1/scale=0.600_distortion=0.850_scene=8", "frame_idx": 48, "probe_touching": false, "probe_location": [203, 185], "gt_bounding_box": [], "mask_idx": 0, "mask_val": 0, "obj_shape_data": [2.456617468225317, 0.683612934054766, 0.28653763976100083], "obj_scaling_data": [4.0, 4.0, 4.0, 8.0], "obj_shape_type": "supertoroid", "obj_location_data": [-5.217309634397894, -2.2875672127015516, 1.947446730182953], "obj_rotation_data": [-0.7330518718298261, 0.003990437302505286, -0.5794297715483795, 0.3562024276451744], "obj_texture_data": {"type": "voronoi", "params": {"Scale": 0.6000000000000001, "Randomness": 0.85}}, "background_texture": {"type": "voronoi", "params": {"Scale": 0.6000000000000001, "Randomness": 0.85}}}, {"image_url": "test_voronoi/superquadric_1/scale=0.600_distortion=1.000_scene=8", "frame_idx": 5, "probe_touching": true, "probe_location": [242, 76], "gt_bounding_box": [[203, 0], [314, 138]], "mask_idx": 0, "mask_val": 40, "obj_shape_data": [2.4232422709702703, 3.8395068102243766, 1.9498922857569052], "obj_scaling_data": [4.0, 4.0, 4.0, 8.0], "obj_shape_type": "superellipsoid", "obj_location_data": [-4.129290654136753, 2.5629005075579685, 8.347740663368267], "obj_rotation_data": [0.969077286229078, 0.19600156280337178, -0.0760431168827485, -0.12918995730426694], "obj_texture_data": {"type": "voronoi", "params": {"Scale": 0.6000000000000001, "Randomness": 1.0}}, "background_texture": {"type": "voronoi", "params": {"Scale": 0.6000000000000001, "Randomness": 1.0}}}, {"image_url": "test_voronoi/superquadric_1/scale=1.000_distortion=0.700_scene=8", "frame_idx": 33, "probe_touching": false, "probe_location": [375, 71], "gt_bounding_box": [], "mask_idx": 0, "mask_val": 0, "obj_shape_data": [0.11198677522857159, 1.5232462998595093, 3.780467870766118], "obj_scaling_data": [4.0, 4.0, 4.0, 8.0], "obj_shape_type": "superellipsoid", "obj_location_data": [12.985403888480544, -0.9379963759476867, 1.1967015975276332], "obj_rotation_data": [-0.07473009358642427, 0.6688443793922473, -0.710655712387502, 0.20501479878041937], "obj_texture_data": {"type": "voronoi", "params": {"Scale": 1.0, "Randomness": 0.7}}, "background_texture": {"type": "voronoi", "params": {"Scale": 1.0, "Randomness": 0.7}}}, {"image_url": "test_voronoi/superquadric_1/scale=1.000_distortion=0.850_scene=8", "frame_idx": 38, "probe_touching": true, "probe_location": [263, 223], "gt_bounding_box": [[188, 140], [300, 260]], "mask_idx": 0, "mask_val": 40, "obj_shape_data": [0.6111212677326705, 0.9405281457376787, 3.636105232401229], "obj_scaling_data": [4.0, 4.0, 4.0, 8.0], "obj_shape_type": "superellipsoid", "obj_location_data": [-7.5732395407275765, 6.112344675250946, -0.8076452590326841], "obj_rotation_data": [-0.3184866502516843, 0.8932845413961161, -0.042531949803928215, -0.31432469670719143], "obj_texture_data": {"type": "voronoi", "params": {"Scale": 1.0, "Randomness": 0.85}}, "background_texture": {"type": "voronoi", "params": {"Scale": 1.0, "Randomness": 0.85}}}, {"image_url": "test_voronoi/superquadric_1/scale=1.000_distortion=1.000_scene=8", "frame_idx": 53, "probe_touching": false, "probe_location": [450, 311], "gt_bounding_box": [], "mask_idx": 0, "mask_val": 0, "obj_shape_data": [0.8919294351079396, 2.7659150647243576, 0.22389243718973925], "obj_scaling_data": [4.0, 4.0, 4.0, 8.0], "obj_shape_type": "superellipsoid", "obj_location_data": [1.3231557483813245, 3.3895608217430127, 0.7802252329568019], "obj_rotation_data": [-0.8782215733702287, 0.029829233129611176, 0.2735471955529786, -0.39116366999392976], "obj_texture_data": {"type": "voronoi", "params": {"Scale": 1.0, "Randomness": 1.0}}, "background_texture": {"type": "voronoi", "params": {"Scale": 1.0, "Randomness": 1.0}}}, {"image_url": "test_voronoi/superquadric_2/scale=0.200_distortion=0.700_scene=8", "frame_idx": 2, "probe_touching": true, "probe_location": [192, 104], "gt_bounding_box": [[5, 28], [511, 255]], "mask_idx": 0, "mask_val": 40, "obj_shape_data": [3.9996883249810162, 0.34867231373208996, 3.5536366889059563], "obj_scaling_data": [3.5, 3.5, 3.5, 7.0], "obj_shape_type": "supertoroid", "obj_location_data": [-0.5887046537558873, 0.09454267494159221, 6.814765198434846], "obj_rotation_data": [0.9950307753654014, 0.06827716166844074, -0.06978135527604733, -0.01955882731831705], "obj_texture_data": {"type": "voronoi", "params": {"Scale": 0.2, "Randomness": 0.7}}, "background_texture": {"type": "voronoi", "params": {"Scale": 0.2, "Randomness": 0.7}}}, {"image_url": "test_voronoi/superquadric_2/scale=0.200_distortion=0.850_scene=8", "frame_idx": 32, "probe_touching": false, "probe_location": [84, 309], "gt_bounding_box": [], "mask_idx": 0, "mask_val": 0, "obj_shape_data": [1.6647467446309536, 2.852351166305408, 3.464816242721913], "obj_scaling_data": [3.5, 3.5, 3.5, 7.0], "obj_shape_type": "supertoroid", "obj_location_data": [-0.2242288438390274, 3.1084071188186084, 2.2722708897217756], "obj_rotation_data": [-0.02493069173807269, 0.8055930279987529, -0.516292280894972, 0.2895524383208138], "obj_texture_data": {"type": "voronoi", "params": {"Scale": 0.2, "Randomness": 0.85}}, "background_texture": {"type": "voronoi", "params": {"Scale": 0.2, "Randomness": 0.85}}}, {"image_url": "test_voronoi/superquadric_2/scale=0.200_distortion=1.000_scene=8", "frame_idx": 63, "probe_touching": true, "probe_location": [182, 63], "gt_bounding_box": [[0, 14], [404, 231]], "mask_idx": 1, "mask_val": 60, "obj_shape_data": [2.1177649670975454, 1.306753403483259, 1.1808363793999406], "obj_scaling_data": [3.5, 3.5, 3.5, 7.0], "obj_shape_type": "supertoroid", "obj_location_data": [-0.6734285950660716, -4.27126359939575, 7.442609786987306], "obj_rotation_data": [-1.0, 1.0441265689292045e-16, -4.0501775872715013e-17, 4.954998545243187e-17], "obj_texture_data": {"type": "voronoi", "params": {"Scale": 0.2, "Randomness": 1.0}}, "background_texture": {"type": "voronoi", "params": {"Scale": 0.2, "Randomness": 1.0}}}, {"image_url": "test_voronoi/superquadric_2/scale=0.600_distortion=0.700_scene=8", "frame_idx": 17, "probe_touching": false, "probe_location": [81, 211], "gt_bounding_box": [], "mask_idx": 0, "mask_val": 0, "obj_shape_data": [1.3443865940245283, 1.6038579239188944, 3.017693933631378], "obj_scaling_data": [3.5, 3.5, 3.5, 7.0], "obj_shape_type": "superellipsoid", "obj_location_data": [7.159925692438985, -2.5257617224805795, 1.6049879031172183], "obj_rotation_data": [0.6616858375968595, -0.5394054707674435, 0.45837186936912194, 0.2472019817900976], "obj_texture_data": {"type": "voronoi", "params": {"Scale": 0.6000000000000001, "Randomness": 0.7}}, "background_texture": {"type": "voronoi", "params": {"Scale": 0.6000000000000001, "Randomness": 0.7}}}, {"image_url": "test_voronoi/superquadric_2/scale=0.600_distortion=0.850_scene=8", "frame_idx": 59, "probe_touching": true, "probe_location": [152, 121], "gt_bounding_box": [[0, 0], [360, 202]], "mask_idx": 1, "mask_val": 60, "obj_shape_data": [3.19001291704729, 2.2363817170388063, 2.505500958568603], "obj_scaling_data": [3.5, 3.5, 3.5, 7.0], "obj_shape_type": "supertoroid", "obj_location_data": [-3.2949698771537648, -0.9188356163785768, 7.626649352493104], "obj_rotation_data": [-0.9801724878485439, 0.16186338629439465, -0.030342143486205318, 0.1101884411849542], "obj_texture_data": {"type": "voronoi", "params": {"Scale": 0.6000000000000001, "Randomness": 0.85}}, "background_texture": {"type": "voronoi", "params": {"Scale": 0.6000000000000001, "Randomness": 0.85}}}, {"image_url": "test_voronoi/superquadric_2/scale=0.600_distortion=1.000_scene=8", "frame_idx": 9, "probe_touching": false, "probe_location": [430, 279], "gt_bounding_box": [], "mask_idx": 0, "mask_val": 0, "obj_shape_data": [3.503956259644512, 2.427580637794619, 2.0959075244308742], "obj_scaling_data": [3.5, 3.5, 3.5, 7.0], "obj_shape_type": "supertoroid", "obj_location_data": [5.9763739258251345, -10.00909074174589, 1.3572881108776642], "obj_rotation_data": [0.9009688679024191, 0.3156874686803698, 0.28901926329287675, -0.07116450403436121], "obj_texture_data": {"type": "voronoi", "params": {"Scale": 0.6000000000000001, "Randomness": 1.0}}, "background_texture": {"type": "voronoi", "params": {"Scale": 0.6000000000000001, "Randomness": 1.0}}}, {"image_url": "test_voronoi/superquadric_2/scale=1.000_distortion=0.700_scene=8", "frame_idx": 19, "probe_touching": true, "probe_location": [420, 190], "gt_bounding_box": [[371, 153], [497, 252]], "mask_idx": 1, "mask_val": 60, "obj_shape_data": [3.7728856792384904, 1.4561775823972318, 2.4670866879183277], "obj_scaling_data": [3.5, 3.5, 3.5, 7.0], "obj_shape_type": "superellipsoid", "obj_location_data": [7.685294994904726, 3.6829913978319726, 3.0294364670142393], "obj_rotation_data": [0.58374367223479, 0.07600991738670575, -0.5929389074856828, -0.5494445100047806], "obj_texture_data": {"type": "voronoi", "params": {"Scale": 1.0, "Randomness": 0.7}}, "background_texture": {"type": "voronoi", "params": {"Scale": 1.0, "Randomness": 0.7}}}, {"image_url": "test_voronoi/superquadric_2/scale=1.000_distortion=0.850_scene=8", "frame_idx": 39, "probe_touching": false, "probe_location": [121, 323], "gt_bounding_box": [], "mask_idx": 0, "mask_val": 0, "obj_shape_data": [2.41417506354487, 3.900663057476561, 2.366656541269586], "obj_scaling_data": [3.5, 3.5, 3.5, 7.0], "obj_shape_type": "supertoroid", "obj_location_data": [4.816650789822986, -6.383691970325024, 4.543172128552429], "obj_rotation_data": [-0.3653410243663951, -0.15134355716065429, 0.6141826981796098, 0.6829353387237237], "obj_texture_data": {"type": "voronoi", "params": {"Scale": 1.0, "Randomness": 0.85}}, "background_texture": {"type": "voronoi", "params": {"Scale": 1.0, "Randomness": 0.85}}}, {"image_url": "test_voronoi/superquadric_2/scale=1.000_distortion=1.000_scene=8", "frame_idx": 29, "probe_touching": true, "probe_location": [120, 437], "gt_bounding_box": [[0, 145], [230, 511]], "mask_idx": 1, "mask_val": 60, "obj_shape_data": [0.3696057713499178, 0.5084268235966083, 2.16556329556426], "obj_scaling_data": [3.5, 3.5, 3.5, 7.0], "obj_shape_type": "supertoroid", "obj_location_data": [-7.32099544636165, -10.326049641536356, -2.4319279294904854], "obj_rotation_data": [0.12434370464748506, 0.9056660084043681, 0.32786252791818193, -0.23835663851157424], "obj_texture_data": {"type": "voronoi", "params": {"Scale": 1.0, "Randomness": 1.0}}, "background_texture": {"type": "voronoi", "params": {"Scale": 1.0, "Randomness": 1.0}}}, {"image_url": "test_voronoi/superquadric_3/scale=0.200_distortion=0.700_scene=8", "frame_idx": 30, "probe_touching": false, "probe_location": [340, 47], "gt_bounding_box": [], "mask_idx": 0, "mask_val": 0, "obj_shape_data": [1.958523591040672, 3.2917256477518415, 3.6066796724559405], "obj_scaling_data": [3.0, 3.0, 3.0, 6.0], "obj_shape_type": "supertoroid", "obj_location_data": [-12.950716140392098, 5.321134369628101, -1.154917811648987], "obj_rotation_data": [0.07473009358642417, 0.6654232033734135, -0.6507716069697794, -0.3579436954142366], "obj_texture_data": {"type": "voronoi", "params": {"Scale": 0.2, "Randomness": 0.7}}, "background_texture": {"type": "voronoi", "params": {"Scale": 0.2, "Randomness": 0.7}}}, {"image_url": "test_voronoi/superquadric_3/scale=0.200_distortion=0.850_scene=8", "frame_idx": 16, "probe_touching": true, "probe_location": [345, 66], "gt_bounding_box": [[200, 0], [459, 95]], "mask_idx": 1, "mask_val": 60, "obj_shape_data": [0.31859631693074636, 0.7476995641197705, 1.9950138111649898], "obj_scaling_data": [3.0, 3.0, 3.0, 6.0], "obj_shape_type": "supertoroid", "obj_location_data": [-3.965387784735542, 7.992436509945204, 16.307955537894166], "obj_rotation_data": [0.6982368180860729, -0.6523087284212052, 0.18543068873095916, 0.22929048905549662], "obj_texture_data": {"type": "voronoi", "params": {"Scale": 0.2, "Randomness": 0.85}}, "background_texture": {"type": "voronoi", "params": {"Scale": 0.2, "Randomness": 0.85}}}, {"image_url": "test_voronoi/superquadric_3/scale=0.200_distortion=1.000_scene=8", "frame_idx": 23, "probe_touching": false, "probe_location": [404, 104], "gt_bounding_box": [], "mask_idx": 0, "mask_val": 0, "obj_shape_data": [3.124977365279426, 2.745810702961044, 3.2188045307427333], "obj_scaling_data": [3.0, 3.0, 3.0, 6.0], "obj_shape_type": "supertoroid", "obj_location_data": [3.1591134967429855, -4.666387810199692, -1.2970615307281328], "obj_rotation_data": [0.4112871031306115, 0.15260526444031422, 0.8924359021796104, 0.10541685142516907], "obj_texture_data": {"type": "voronoi", "params": {"Scale": 0.2, "Randomness": 1.0}}, "background_texture": {"type": "voronoi", "params": {"Scale": 0.2, "Randomness": 1.0}}}, {"image_url": "test_voronoi/superquadric_3/scale=0.600_distortion=0.700_scene=8", "frame_idx": 4, "probe_touching": true, "probe_location": [186, 296], "gt_bounding_box": [[118, 169], [398, 335]], "mask_idx": 0, "mask_val": 40, "obj_shape_data": [2.3151611747370624, 3.393037000238409, 3.058573110869764], "obj_scaling_data": [3.0, 3.0, 3.0, 6.0], "obj_shape_type": "supertoroid", "obj_location_data": [0.4808039186379414, -0.2234668128334536, 0.20291095083279606], "obj_rotation_data": [0.9801724878485438, 0.011607346096363519, -0.1827196422830151, -0.07576738021973836], "obj_texture_data": {"type": "voronoi", "params": {"Scale": 0.6000000000000001, "Randomness": 0.7}}, "background_texture": {"type": "voronoi", "params": {"Scale": 0.6000000000000001, "Randomness": 0.7}}}, {"image_url": "test_voronoi/superquadric_3/scale=0.600_distortion=0.850_scene=8", "frame_idx": 45, "probe_touching": false, "probe_location": [149, 110], "gt_bounding_box": [], "mask_idx": 0, "mask_val": 0, "obj_shape_data": [0.4155129797431314, 0.5934040633430445, 1.8420104106883537], "obj_scaling_data": [3.0, 3.0, 3.0, 6.0], "obj_shape_type": "superellipsoid", "obj_location_data": [-0.5059121285876115, -4.455771815918519, -6.858193255196852], "obj_rotation_data": [-0.6234898018587335, -0.7796264365272702, 0.058278654346987736, 0.00683263444450462], "obj_texture_data": {"type": "voronoi", "params": {"Scale": 0.6000000000000001, "Randomness": 0.85}}, "background_texture": {"type": "voronoi", "params": {"Scale": 0.6000000000000001, "Randomness": 0.85}}}, {"image_url": "test_voronoi/superquadric_3/scale=0.600_distortion=1.000_scene=8", "frame_idx": 11, "probe_touching": true, "probe_location": [200, 126], "gt_bounding_box": [[8, 0], [300, 166]], "mask_idx": 1, "mask_val": 60, "obj_shape_data": [3.033134029499874, 1.340908597472243, 1.4561712238261675], "obj_scaling_data": [3.0, 3.0, 3.0, 6.0], "obj_shape_type": "supertoroid", "obj_location_data": [-9.202938378816592, 1.3368599539825785, 9.293138442509644], "obj_rotation_data": [0.8532908816321556, 0.204616850985595, 0.330965676376192, 0.34711429915376163], "obj_texture_data": {"type": "voronoi", "params": {"Scale": 0.6000000000000001, "Randomness": 1.0}}, "background_texture": {"type": "voronoi", "params": {"Scale": 0.6000000000000001, "Randomness": 1.0}}}, {"image_url": "test_voronoi/superquadric_3/scale=1.000_distortion=0.700_scene=8", "frame_idx": 2, "probe_touching": false, "probe_location": [296, 401], "gt_bounding_box": [], "mask_idx": 0, "mask_val": 0, "obj_shape_data": [2.356649601151792, 1.8255807617157607, 1.092962206819515], "obj_scaling_data": [3.0, 3.0, 3.0, 6.0], "obj_shape_type": "supertoroid", "obj_location_data": [-1.350768779868331, 8.074449028557373, -4.131811571585333], "obj_rotation_data": [0.9950307753654014, -0.05884070040829144, 0.08031826683618494, -0.0007099743806393348], "obj_texture_data": {"type": "voronoi", "params": {"Scale": 1.0, "Randomness": 0.7}}, "background_texture": {"type": "voronoi", "params": {"Scale": 1.0, "Randomness": 0.7}}}, {"image_url": "test_voronoi/superquadric_3/scale=1.000_distortion=0.850_scene=8", "frame_idx": 11, "probe_touching": true, "probe_location": [163, 390], "gt_bounding_box": [[0, 268], [253, 511]], "mask_idx": 0, "mask_val": 40, "obj_shape_data": [3.853909394337603, 3.509587629222755, 1.932665509891879], "obj_scaling_data": [3.0, 3.0, 3.0, 6.0], "obj_shape_type": "supertoroid", "obj_location_data": [2.12268249901132, -10.67552094417785, -5.452237408772225], "obj_rotation_data": [0.8532908816321556, -0.30767047200744807, 0.4209495636880699, -0.005917500228665506], "obj_texture_data": {"type": "voronoi", "params": {"Scale": 1.0, "Randomness": 0.85}}, "background_texture": {"type": "voronoi", "params": {"Scale": 1.0, "Randomness": 0.85}}}, {"image_url": "test_voronoi/superquadric_3/scale=1.000_distortion=1.000_scene=8", "frame_idx": 49, "probe_touching": false, "probe_location": [255, 90], "gt_bounding_box": [], "mask_idx": 0, "mask_val": 0, "obj_shape_data": [0.2440929708853929, 2.400341874325215, 1.2871155126731786], "obj_scaling_data": [3.0, 3.0, 3.0, 6.0], "obj_shape_type": "supertoroid", "obj_location_data": [6.216626419993522, -1.0130382181670587, -4.330378333229316], "obj_rotation_data": [-0.7660444431189779, -0.358308880868497, 0.23989409895047653, 0.4766985193453398], "obj_texture_data": {"type": "voronoi", "params": {"Scale": 1.0, "Randomness": 1.0}}, "background_texture": {"type": "voronoi", "params": {"Scale": 1.0, "Randomness": 1.0}}}, {"image_url": "test_voronoi/superquadric_4/scale=0.200_distortion=0.700_scene=8", "frame_idx": 10, "probe_touching": true, "probe_location": [372, 188], "gt_bounding_box": [[328, 147], [423, 238]], "mask_idx": 2, "mask_val": 80, "obj_shape_data": [2.0273522095245995, 1.9285770516931537, 3.148780772883619], "obj_scaling_data": [2.5, 2.5, 2.5, 5.0], "obj_shape_type": "superellipsoid", "obj_location_data": [5.960045691545884, 1.2680978609807623, 4.309784824179536], "obj_rotation_data": [0.8782215733702285, 0.03291478894890758, 0.3843900606291932, -0.28264423932755883], "obj_texture_data": {"type": "voronoi", "params": {"Scale": 0.2, "Randomness": 0.7}}, "background_texture": {"type": "voronoi", "params": {"Scale": 0.2, "Randomness": 0.7}}}, {"image_url": "test_voronoi/superquadric_4/scale=0.200_distortion=0.850_scene=8", "frame_idx": 13, "probe_touching": false, "probe_location": [276, 264], "gt_bounding_box": [], "mask_idx": 0, "mask_val": 0, "obj_shape_data": [3.551010468399018, 1.6788587323410507, 3.0474363518510614], "obj_scaling_data": [2.5, 2.5, 2.5, 5.0], "obj_shape_type": "supertoroid", "obj_location_data": [-0.4258781106814938, -5.056544804755661, 6.369176291636019], "obj_rotation_data": [0.7971325072229225, 0.3241541760105506, -0.31731313506451325, 0.3985175158245224], "obj_texture_data": {"type": "voronoi", "params": {"Scale": 0.2, "Randomness": 0.85}}, "background_texture": {"type": "voronoi", "params": {"Scale": 0.2, "Randomness": 0.85}}}, {"image_url": "test_voronoi/superquadric_4/scale=0.200_distortion=1.000_scene=8", "frame_idx": 30, "probe_touching": true, "probe_location": [426, 132], "gt_bounding_box": [[172, 0], [511, 220]], "mask_idx": 1, "mask_val": 60, "obj_shape_data": [0.5179452077711024, 0.18592764726490446, 3.910843738300048], "obj_scaling_data": [2.5, 2.5, 2.5, 5.0], "obj_shape_type": "supertoroid", "obj_location_data": [3.3692317896702475, 3.0242246016229517, 7.758555662798696], "obj_rotation_data": [0.07473009358642417, 0.1423074928422323, -0.42962731454569875, -0.8885855958711989], "obj_texture_data": {"type": "voronoi", "params": {"Scale": 0.2, "Randomness": 1.0}}, "background_texture": {"type": "voronoi", "params": {"Scale": 0.2, "Randomness": 1.0}}}, {"image_url": "test_voronoi/superquadric_4/scale=0.600_distortion=0.700_scene=8", "frame_idx": 47, "probe_touching": false, "probe_location": [453, 457], "gt_bounding_box": [], "mask_idx": 0, "mask_val": 0, "obj_shape_data": [2.3492973321444217, 2.678889114182506, 0.1042788333629147], "obj_scaling_data": [2.5, 2.5, 2.5, 5.0], "obj_shape_type": "supertoroid", "obj_location_data": [7.585026005172223, 9.815459535633753, 4.511141000733409], "obj_rotation_data": [-0.6982368180860724, -0.6993310893293231, -0.13094083149570865, 0.0790940706609017], "obj_texture_data": {"type": "voronoi", "params": {"Scale": 0.6000000000000001, "Randomness": 0.7}}, "background_texture": {"type": "voronoi", "params": {"Scale": 0.6000000000000001, "Randomness": 0.7}}}, {"image_url": "test_voronoi/superquadric_4/scale=0.600_distortion=0.850_scene=8", "frame_idx": 32, "probe_touching": true, "probe_location": [368, 213], "gt_bounding_box": [[121, 135], [403, 379]], "mask_idx": 0, "mask_val": 40, "obj_shape_data": [0.3426595993887403, 1.0043985085380085, 1.3633760690758443], "obj_scaling_data": [2.5, 2.5, 2.5, 5.0], "obj_shape_type": "supertoroid", "obj_location_data": [-0.08649301168658725, -0.23166209653038294, 0.0843921039208654], "obj_rotation_data": [-0.02493069173807269, -0.685944911816905, 0.7036709240012566, 0.18358994873678983], "obj_texture_data": {"type": "voronoi", "params": {"Scale": 0.6000000000000001, "Randomness": 0.85}}, "background_texture": {"type": "voronoi", "params": {"Scale": 0.6000000000000001, "Randomness": 0.85}}}, {"image_url": "test_voronoi/superquadric_4/scale=0.600_distortion=1.000_scene=8", "frame_idx": 1, "probe_touching": false, "probe_location": [401, 467], "gt_bounding_box": [], "mask_idx": 0, "mask_val": 0, "obj_shape_data": [1.673480613509055, 1.897669228542032, 3.428264637897126], "obj_scaling_data": [2.5, 2.5, 2.5, 5.0], "obj_shape_type": "supertoroid", "obj_location_data": [0.42062419329641776, -0.6281091951071605, 9.44535666790735], "obj_rotation_data": [0.9987569212189223, -0.033079336634997104, 0.03532696207499992, -0.011932122847144578], "obj_texture_data": {"type": "voronoi", "params": {"Scale": 0.6000000000000001, "Randomness": 1.0}}, "background_texture": {"type": "voronoi", "params": {"Scale": 0.6000000000000001, "Randomness": 1.0}}}, {"image_url": "test_voronoi/superquadric_4/scale=1.000_distortion=0.700_scene=8", "frame_idx": 14, "probe_touching": true, "probe_location": [199, 429], "gt_bounding_box": [[145, 330], [285, 461]], "mask_idx": 2, "mask_val": 80, "obj_shape_data": [1.477664615018185, 2.1549400985243623, 1.5479542725595972], "obj_scaling_data": [2.5, 2.5, 2.5, 5.0], "obj_shape_type": "supertoroid", "obj_location_data": [-1.070382863375422, -2.3941158636167956, -7.936115672796692], "obj_rotation_data": [0.766044443118978, 0.125459129606169, -0.6220898202056114, 0.10217716751577754], "obj_texture_data": {"type": "voronoi", "params": {"Scale": 1.0, "Randomness": 0.7}}, "background_texture": {"type": "voronoi", "params": {"Scale": 1.0, "Randomness": 0.7}}}, {"image_url": "test_voronoi/superquadric_4/scale=1.000_distortion=0.850_scene=8", "frame_idx": 43, "probe_touching": false, "probe_location": [246, 466], "gt_bounding_box": [], "mask_idx": 0, "mask_val": 0, "obj_shape_data": [3.688110052237066, 1.0367153926242483, 1.6270938714601042], "obj_scaling_data": [2.5, 2.5, 2.5, 5.0], "obj_shape_type": "superellipsoid", "obj_location_data": [-8.617041038644139, 3.832251730506452, 2.647326670275318], "obj_rotation_data": [-0.5425462638657593, 0.6005075158089737, -0.07786717275826684, -0.5822121421173518], "obj_texture_data": {"type": "voronoi", "params": {"Scale": 1.0, "Randomness": 0.85}}, "background_texture": {"type": "voronoi", "params": {"Scale": 1.0, "Randomness": 0.85}}}, {"image_url": "test_voronoi/superquadric_4/scale=1.000_distortion=1.000_scene=8", "frame_idx": 56, "probe_touching": true, "probe_location": [437, 284], "gt_bounding_box": [[180, 78], [511, 332]], "mask_idx": 0, "mask_val": 40, "obj_shape_data": [0.9687826869313769, 2.1583282600538283, 3.6140033601919948], "obj_scaling_data": [2.5, 2.5, 2.5, 5.0], "obj_shape_type": "supertoroid", "obj_location_data": [11.760031273428309, -3.8499665411831807, 5.787213877103044], "obj_rotation_data": [-0.9396926207859083, -0.07450357245305644, 0.18787609688686485, 0.2759158718718454], "obj_texture_data": {"type": "voronoi", "params": {"Scale": 1.0, "Randomness": 1.0}}, "background_texture": {"type": "voronoi", "params": {"Scale": 1.0, "Randomness": 1.0}}}, {"image_url": "test_noise/superquadric_1/scale=0.250_distortion=0.200_scene=8", "frame_idx": 63, "probe_touching": false, "probe_location": [148, 129], "gt_bounding_box": [], "mask_idx": 0, "mask_val": 0, "obj_shape_data": [1.9454703852163417, 2.206523472514936, 1.8385150522436258], "obj_scaling_data": [4.0, 4.0, 4.0, 8.0], "obj_shape_type": "superellipsoid", "obj_location_data": [4.115100383758545, 0.505354285240173, -1.0983285903930662], "obj_rotation_data": [-1.0, 9.017793239427754e-17, 8.14228542778965e-17, 1.5357640995677608e-17], "obj_texture_data": {"type": "noise", "params": {"Scale": 0.25, "Distortion": 0.2, "Detail": 1.3039801267173012, "Roughness": 0.6200346938216761}}, "background_texture": {"type": "noise", "params": {"Scale": 0.25, "Distortion": 0.2, "Detail": 1.1377588286678593, "Roughness": 0.4686531085835096}}}, {"image_url": "test_noise/superquadric_1/scale=0.250_distortion=2.100_scene=8", "frame_idx": 21, "probe_touching": true, "probe_location": [325, 362], "gt_bounding_box": [[108, 97], [511, 511]], "mask_idx": 0, "mask_val": 40, "obj_shape_data": [2.6928431723773936, 3.764443888009912, 2.2216920427552562], "obj_scaling_data": [4.0, 4.0, 4.0, 8.0], "obj_shape_type": "supertoroid", "obj_location_data": [4.052006026325203, -1.7048709269087967, -1.0796224411266173], "obj_rotation_data": [0.5000000000000001, 0.41036510524340963, -0.18361704431993936, 0.7401927191169706], "obj_texture_data": {"type": "noise", "params": {"Scale": 0.25, "Distortion": 2.1, "Detail": 1.1578193972140989, "Roughness": 0.3191301972731526}}, "background_texture": {"type": "noise", "params": {"Scale": 0.25, "Distortion": 2.1, "Detail": 1.595258275050361, "Roughness": 0.2384265214153306}}}, {"image_url": "test_noise/superquadric_1/scale=0.250_distortion=4.000_scene=8", "frame_idx": 4, "probe_touching": false, "probe_location": [286, 331], "gt_bounding_box": [], "mask_idx": 0, "mask_val": 0, "obj_shape_data": [1.5009278555737917, 0.8297756895663124, 1.5092698636137871], "obj_scaling_data": [4.0, 4.0, 4.0, 8.0], "obj_shape_type": "superellipsoid", "obj_location_data": [2.38964298283708, 0.19657742848111348, 1.505697487513429], "obj_rotation_data": [0.9801724878485438, 0.13937400120966065, -0.07657393903897101, 0.11820834873925623], "obj_texture_data": {"type": "noise", "params": {"Scale": 0.25, "Distortion": 4.0, "Detail": 1.3439367427337259, "Roughness": 0.4743621082474263}}, "background_texture": {"type": "noise", "params": {"Scale": 0.25, "Distortion": 4.0, "Detail": 1.4055813274981035, "Roughness": 0.9864070512513763}}}, {"image_url": "test_noise/superquadric_1/scale=0.625_distortion=0.200_scene=8", "frame_idx": 12, "probe_touching": true, "probe_location": [296, 354], "gt_bounding_box": [[232, 265], [356, 404]], "mask_idx": 0, "mask_val": 40, "obj_shape_data": [2.3248165770737534, 2.551511098041544, 1.7117772569521568], "obj_scaling_data": [4.0, 4.0, 4.0, 8.0], "obj_shape_type": "superellipsoid", "obj_location_data": [3.752136955832923, -1.6831327846679667, -2.8862541258327092], "obj_rotation_data": [0.8262387743159949, -0.32974966218434154, 0.4042166402255486, -0.21261127879509226], "obj_texture_data": {"type": "noise", "params": {"Scale": 0.625, "Distortion": 0.2, "Detail": 1.9097359717419624, "Roughness": 0.6822171942494167}}, "background_texture": {"type": "noise", "params": {"Scale": 0.625, "Distortion": 0.2, "Detail": 1.5170006006779349, "Roughness": 0.7308903054600242}}}, {"image_url": "test_noise/superquadric_1/scale=0.625_distortion=2.100_scene=8", "frame_idx": 62, "probe_touching": false, "probe_location": [69, 51], "gt_bounding_box": [], "mask_idx": 0, "mask_val": 0, "obj_shape_data": [2.157486992167202, 0.3916412106774057, 1.7970330123759293], "obj_scaling_data": [4.0, 4.0, 4.0, 8.0], "obj_shape_type": "supertoroid", "obj_location_data": [3.278172969371695, -2.2935267012945424, -1.394327215736404], "obj_rotation_data": [-0.9987569212189223, 0.02210580767487237, 0.03467585712294877, -0.028169673713582914], "obj_texture_data": {"type": "noise", "params": {"Scale": 0.625, "Distortion": 2.1, "Detail": 1.7375483836265424, "Roughness": 0.617630740682818}}, "background_texture": {"type": "noise", "params": {"Scale": 0.625, "Distortion": 2.1, "Detail": 1.3529889819002183, "Roughness": 0.33802415433107963}}}, {"image_url": "test_noise/superquadric_1/scale=0.625_distortion=4.000_scene=8", "frame_idx": 31, "probe_touching": true, "probe_location": [212, 292], "gt_bounding_box": [[148, 232], [246, 335]], "mask_idx": 0, "mask_val": 40, "obj_shape_data": [1.0911184953923525, 3.292113802649607, 3.187382797792759], "obj_scaling_data": [4.0, 4.0, 4.0, 8.0], "obj_shape_type": "superellipsoid", "obj_location_data": [-3.2447986385476852, -2.7985221670490077, -3.1540059964482734], "obj_rotation_data": [0.024930691738073035, -0.2133735909669736, 0.13868493315237948, -0.9667557398866787], "obj_texture_data": {"type": "noise", "params": {"Scale": 0.625, "Distortion": 4.0, "Detail": 1.0866890173395607, "Roughness": 0.3195656898351897}}, "background_texture": {"type": "noise", "params": {"Scale": 0.625, "Distortion": 4.0, "Detail": 1.0817949291953086, "Roughness": 0.24763182774391146}}}, {"image_url": "test_noise/superquadric_1/scale=1.000_distortion=0.200_scene=8", "frame_idx": 6, "probe_touching": false, "probe_location": [315, 246], "gt_bounding_box": [], "mask_idx": 0, "mask_val": 0, "obj_shape_data": [2.587442107852448, 1.4840005041651851, 1.256313851738791], "obj_scaling_data": [4.0, 4.0, 4.0, 8.0], "obj_shape_type": "superellipsoid", "obj_location_data": [-0.6217181832008564, -2.232467342654356, 4.232407474149501], "obj_rotation_data": [0.9555728057861408, -0.1890577601381307, -0.1645482250220796, 0.15511820594513923], "obj_texture_data": {"type": "noise", "params": {"Scale": 1.0, "Distortion": 0.2, "Detail": 1.2035612549772932, "Roughness": 0.23247100510118168}}, "background_texture": {"type": "noise", "params": {"Scale": 1.0, "Distortion": 0.2, "Detail": 1.4537695517603721, "Roughness": 0.29720535326406106}}}, {"image_url": "test_noise/superquadric_1/scale=1.000_distortion=2.100_scene=8", "frame_idx": 11, "probe_touching": true, "probe_location": [352, 181], "gt_bounding_box": [[131, 144], [511, 511]], "mask_idx": 0, "mask_val": 40, "obj_shape_data": [2.0779633675090943, 1.2287347607574928, 0.39488162051728326], "obj_scaling_data": [4.0, 4.0, 4.0, 8.0], "obj_shape_type": "supertoroid", "obj_location_data": [2.824649504658394, 2.6612499196303663, -5.304883176313928], "obj_rotation_data": [0.8532908816321556, 0.1750482275485299, 0.4292844560457143, -0.2386789583374953], "obj_texture_data": {"type": "noise", "params": {"Scale": 1.0, "Distortion": 2.1, "Detail": 1.6696188382494146, "Roughness": 0.8133947830439514}}, "background_texture": {"type": "noise", "params": {"Scale": 1.0, "Distortion": 2.1, "Detail": 1.109185276993285, "Roughness": 0.8240510145775064}}}, {"image_url": "test_noise/superquadric_1/scale=1.000_distortion=4.000_scene=8", "frame_idx": 14, "probe_touching": false, "probe_location": [50, 327], "gt_bounding_box": [], "mask_idx": 0, "mask_val": 0, "obj_shape_data": [0.780462209984655, 1.2126712793364023, 3.654590608982116], "obj_scaling_data": [4.0, 4.0, 4.0, 8.0], "obj_shape_type": "superellipsoid", "obj_location_data": [-0.7064281261745256, -4.166312983708688, 0.06028062578342863], "obj_rotation_data": [0.766044443118978, -0.5279751136283388, 0.14141318103389128, 0.33826099802601156], "obj_texture_data": {"type": "noise", "params": {"Scale": 1.0, "Distortion": 4.0, "Detail": 1.295372793629974, "Roughness": 0.6437972334387864}}, "background_texture": {"type": "noise", "params": {"Scale": 1.0, "Distortion": 4.0, "Detail": 1.0606236719739368, "Roughness": 0.49748256384094863}}}, {"image_url": "test_noise/superquadric_2/scale=0.250_distortion=0.200_scene=8", "frame_idx": 56, "probe_touching": true, "probe_location": [156, 263], "gt_bounding_box": [[128, 198], [231, 308]], "mask_idx": 0, "mask_val": 40, "obj_shape_data": [0.3331488632754188, 2.1488119046456844, 3.010616842128672], "obj_scaling_data": [3.5, 3.5, 3.5, 7.0], "obj_shape_type": "superellipsoid", "obj_location_data": [-7.8166627618701625, -0.3369764113450074, -3.737107509003677], "obj_rotation_data": [-0.9396926207859083, 0.20874092736991065, 0.23297021001876178, 0.1383108272156406], "obj_texture_data": {"type": "noise", "params": {"Scale": 0.25, "Distortion": 0.2, "Detail": 1.9422028086400607, "Roughness": 0.638281977675246}}, "background_texture": {"type": "noise", "params": {"Scale": 0.25, "Distortion": 0.2, "Detail": 1.612226072101184, "Roughness": 0.35468186849794336}}}, {"image_url": "test_noise/superquadric_2/scale=0.250_distortion=2.100_scene=8", "frame_idx": 30, "probe_touching": false, "probe_location": [358, 417], "gt_bounding_box": [], "mask_idx": 0, "mask_val": 0, "obj_shape_data": [3.7475030562154306, 1.6413718295042976, 0.3855582755745441], "obj_scaling_data": [3.5, 3.5, 3.5, 7.0], "obj_shape_type": "supertoroid", "obj_location_data": [4.148016704938089, 12.622996985399773, -0.42612136921075616], "obj_rotation_data": [0.07473009358642417, -0.7905535122622434, 0.28854610131327724, 0.5349595356466724], "obj_texture_data": {"type": "noise", "params": {"Scale": 0.25, "Distortion": 2.1, "Detail": 1.3688936620432732, "Roughness": 0.7596650415200255}}, "background_texture": {"type": "noise", "params": {"Scale": 0.25, "Distortion": 2.1, "Detail": 1.914033284939593, "Roughness": 0.20162952199007106}}}, {"image_url": "test_noise/superquadric_2/scale=0.250_distortion=4.000_scene=8", "frame_idx": 5, "probe_touching": true, "probe_location": [256, 278], "gt_bounding_box": [[95, 197], [351, 416]], "mask_idx": 0, "mask_val": 40, "obj_shape_data": [2.6215270523934096, 3.1637146948079136, 1.6916543470140262], "obj_scaling_data": [3.5, 3.5, 3.5, 7.0], "obj_shape_type": "supertoroid", "obj_location_data": [-3.177514088167325, 1.5151343025004473, -4.768920092303789], "obj_rotation_data": [0.969077286229078, -0.16900119976113173, 0.15561569379436735, -0.09006421952740988], "obj_texture_data": {"type": "noise", "params": {"Scale": 0.25, "Distortion": 4.0, "Detail": 1.7639006674676738, "Roughness": 0.5561085840727746}}, "background_texture": {"type": "noise", "params": {"Scale": 0.25, "Distortion": 4.0, "Detail": 1.4978540909263478, "Roughness": 0.6168940993034664}}}, {"image_url": "test_noise/superquadric_2/scale=0.625_distortion=0.200_scene=8", "frame_idx": 33, "probe_touching": false, "probe_location": [352, 429], "gt_bounding_box": [], "mask_idx": 0, "mask_val": 0, "obj_shape_data": [0.5399108682096685, 0.4378095257241854, 1.9364426535388644], "obj_scaling_data": [3.5, 3.5, 3.5, 7.0], "obj_shape_type": "supertoroid", "obj_location_data": [-2.045277223789359, -9.070113558149545, 6.275740010469781], "obj_rotation_data": [-0.07473009358642427, -0.5527085303228607, -0.3777287771867347, -0.7390870479895596], "obj_texture_data": {"type": "noise", "params": {"Scale": 0.625, "Distortion": 0.2, "Detail": 1.9441530923488086, "Roughness": 0.5760915306346484}}, "background_texture": {"type": "noise", "params": {"Scale": 0.625, "Distortion": 0.2, "Detail": 1.1891333308444745, "Roughness": 0.6682067587965412}}}, {"image_url": "test_noise/superquadric_2/scale=0.625_distortion=2.100_scene=8", "frame_idx": 45, "probe_touching": true, "probe_location": [298, 95], "gt_bounding_box": [[248, 45], [486, 269]], "mask_idx": 1, "mask_val": 60, "obj_shape_data": [2.025817447950768, 1.9629140836823182, 1.6691406021574449], "obj_scaling_data": [3.5, 3.5, 3.5, 7.0], "obj_shape_type": "supertoroid", "obj_location_data": [-2.859703168289579, 11.21099681392911, 2.956098773873162], "obj_rotation_data": [-0.6234898018587335, -0.4238184706298277, 0.4323476257324947, -0.4946856592368795], "obj_texture_data": {"type": "noise", "params": {"Scale": 0.625, "Distortion": 2.1, "Detail": 1.6019441093777038, "Roughness": 0.7405315274874349}}, "background_texture": {"type": "noise", "params": {"Scale": 0.625, "Distortion": 2.1, "Detail": 1.7250329570745184, "Roughness": 0.4478813597335507}}}, {"image_url": "test_noise/superquadric_2/scale=0.625_distortion=4.000_scene=8", "frame_idx": 17, "probe_touching": false, "probe_location": [437, 161], "gt_bounding_box": [], "mask_idx": 0, "mask_val": 0, "obj_shape_data": [3.8953658221092313, 2.1566232728815526, 1.7521690935981964], "obj_scaling_data": [3.5, 3.5, 3.5, 7.0], "obj_shape_type": "supertoroid", "obj_location_data": [-3.8901827442883268, 9.78541721270762, -3.266783436539268], "obj_rotation_data": [0.6616858375968595, 0.7140425405946851, 0.1065794797949662, 0.20237568290549257], "obj_texture_data": {"type": "noise", "params": {"Scale": 0.625, "Distortion": 4.0, "Detail": 1.860331878123855, "Roughness": 0.6043511944793476}}, "background_texture": {"type": "noise", "params": {"Scale": 0.625, "Distortion": 4.0, "Detail": 1.4348079188868104, "Roughness": 0.2684052909910607}}}, {"image_url": "test_noise/superquadric_2/scale=1.000_distortion=0.200_scene=8", "frame_idx": 23, "probe_touching": true, "probe_location": [239, 109], "gt_bounding_box": [[151, 0], [397, 239]], "mask_idx": 1, "mask_val": 60, "obj_shape_data": [1.3409720190936065, 3.0537758387256266, 2.290740411954949], "obj_scaling_data": [3.5, 3.5, 3.5, 7.0], "obj_shape_type": "supertoroid", "obj_location_data": [-5.357870688732562, 5.153538217445275, 5.543672039842409], "obj_rotation_data": [0.4112871031306115, -0.16911903805063982, 0.8888326620246397, -0.11053582534838301], "obj_texture_data": {"type": "noise", "params": {"Scale": 1.0, "Distortion": 0.2, "Detail": 1.050469728162565, "Roughness": 0.5677825591746043}}, "background_texture": {"type": "noise", "params": {"Scale": 1.0, "Distortion": 0.2, "Detail": 1.6206703715400304, "Roughness": 0.31622303595297796}}}, {"image_url": "test_noise/superquadric_2/scale=1.000_distortion=2.100_scene=8", "frame_idx": 23, "probe_touching": false, "probe_location": [363, 249], "gt_bounding_box": [], "mask_idx": 0, "mask_val": 0, "obj_shape_data": [3.659649054627503, 3.2333145914841435, 0.7182103774338866], "obj_scaling_data": [3.5, 3.5, 3.5, 7.0], "obj_shape_type": "superellipsoid", "obj_location_data": [16.5461921095484, -13.311973994643184, -1.0700337829412245], "obj_rotation_data": [0.4112871031306115, 0.9051787531894294, 0.08182921367836776, 0.0692699311508231], "obj_texture_data": {"type": "noise", "params": {"Scale": 1.0, "Distortion": 2.1, "Detail": 1.1453780502447972, "Roughness": 0.7025608865065656}}, "background_texture": {"type": "noise", "params": {"Scale": 1.0, "Distortion": 2.1, "Detail": 1.7747094546367608, "Roughness": 0.4851062918726454}}}, {"image_url": "test_noise/superquadric_2/scale=1.000_distortion=4.000_scene=8", "frame_idx": 45, "probe_touching": true, "probe_location": [305, 310], "gt_bounding_box": [[83, 189], [347, 480]], "mask_idx": 0, "mask_val": 40, "obj_shape_data": [3.9076341747573986, 2.297754566278323, 1.6361981992066772], "obj_scaling_data": [3.5, 3.5, 3.5, 7.0], "obj_shape_type": "supertoroid", "obj_location_data": [-1.5478057031334902, -0.4977050356464736, -8.305609096468338], "obj_rotation_data": [-0.6234898018587335, -0.4288828990683117, -0.47297600679014185, -0.451235662227366], "obj_texture_data": {"type": "noise", "params": {"Scale": 1.0, "Distortion": 4.0, "Detail": 1.399968977930917, "Roughness": 0.2784130134167726}}, "background_texture": {"type": "noise", "params": {"Scale": 1.0, "Distortion": 4.0, "Detail": 1.9436014428692479, "Roughness": 0.7789411627344078}}}, {"image_url": "test_noise/superquadric_3/scale=0.250_distortion=0.200_scene=8", "frame_idx": 40, "probe_touching": false, "probe_location": [429, 411], "gt_bounding_box": [], "mask_idx": 0, "mask_val": 0, "obj_shape_data": [1.940609182430693, 0.013195403814072372, 0.9490480621352553], "obj_scaling_data": [3.0, 3.0, 3.0, 6.0], "obj_shape_type": "superellipsoid", "obj_location_data": [-1.2088043418774783, -0.3373378283694744, 2.9958490206455717], "obj_rotation_data": [-0.4112871031306118, 0.3100696129576267, 0.7294983846165889, 0.45003539945267035], "obj_texture_data": {"type": "noise", "params": {"Scale": 0.25, "Distortion": 0.2, "Detail": 1.400508497642925, "Roughness": 0.7988648457784022}}, "background_texture": {"type": "noise", "params": {"Scale": 0.25, "Distortion": 0.2, "Detail": 1.3777109743867602, "Roughness": 0.2754691901590314}}}, {"image_url": "test_noise/superquadric_3/scale=0.250_distortion=2.100_scene=8", "frame_idx": 32, "probe_touching": true, "probe_location": [92, 161], "gt_bounding_box": [[0, 81], [262, 221]], "mask_idx": 0, "mask_val": 40, "obj_shape_data": [3.9364165247830214, 3.4260769767043677, 3.585070983942695], "obj_scaling_data": [3.0, 3.0, 3.0, 6.0], "obj_shape_type": "supertoroid", "obj_location_data": [-7.734598422807881, -5.555757042601785, 5.054701090145232], "obj_rotation_data": [-0.02493069173807269, 0.9123751308241819, -0.40556971787902196, 0.049631494059203356], "obj_texture_data": {"type": "noise", "params": {"Scale": 0.25, "Distortion": 2.1, "Detail": 1.8820447655732564, "Roughness": 0.5385994247385393}}, "background_texture": {"type": "noise", "params": {"Scale": 0.25, "Distortion": 2.1, "Detail": 1.375736058901806, "Roughness": 0.8914313567240268}}}, {"image_url": "test_noise/superquadric_3/scale=0.250_distortion=4.000_scene=8", "frame_idx": 31, "probe_touching": false, "probe_location": [128, 180], "gt_bounding_box": [], "mask_idx": 0, "mask_val": 0, "obj_shape_data": [2.5908391216962423, 3.8055858835126646, 0.8979693381522944], "obj_scaling_data": [3.0, 3.0, 3.0, 6.0], "obj_shape_type": "superellipsoid", "obj_location_data": [-3.6466877221270115, 2.9473920946131873, 8.492127757006356], "obj_rotation_data": [0.024930691738073035, -0.050174226596289645, 0.7731657027190283, 0.6317244682089784], "obj_texture_data": {"type": "noise", "params": {"Scale": 0.25, "Distortion": 4.0, "Detail": 1.0958589704836743, "Roughness": 0.8431614711880289}}, "background_texture": {"type": "noise", "params": {"Scale": 0.25, "Distortion": 4.0, "Detail": 1.9702003108023702, "Roughness": 0.6951705896485256}}}, {"image_url": "test_noise/superquadric_3/scale=0.625_distortion=0.200_scene=8", "frame_idx": 58, "probe_touching": true, "probe_location": [260, 132], "gt_bounding_box": [[206, 88], [303, 198]], "mask_idx": 1, "mask_val": 60, "obj_shape_data": [1.8019110912228897, 3.773456113855746, 0.529295583703435], "obj_scaling_data": [3.0, 3.0, 3.0, 6.0], "obj_shape_type": "superellipsoid", "obj_location_data": [2.1115107950014376, -2.765464902438488, 7.013918223134659], "obj_rotation_data": [-0.969077286229078, -0.2218454222086986, 0.09549497625481242, -0.050542373015349286], "obj_texture_data": {"type": "noise", "params": {"Scale": 0.625, "Distortion": 0.2, "Detail": 1.2267370965510822, "Roughness": 0.38895091791298003}}, "background_texture": {"type": "noise", "params": {"Scale": 0.625, "Distortion": 0.2, "Detail": 1.3449328766758404, "Roughness": 0.3913029531629528}}}, {"image_url": "test_noise/superquadric_3/scale=0.625_distortion=2.100_scene=8", "frame_idx": 2, "probe_touching": false, "probe_location": [118, 186], "gt_bounding_box": [], "mask_idx": 0, "mask_val": 0, "obj_shape_data": [1.3744002671757074, 3.626749234224563, 2.438717604561597], "obj_scaling_data": [3.0, 3.0, 3.0, 6.0], "obj_shape_type": "superellipsoid", "obj_location_data": [6.5831219859829275, -9.599097488937009, 0.315581449148949], "obj_rotation_data": [0.9950307753654014, -0.09240678278677542, 0.007267748989272307, 0.03635825071912447], "obj_texture_data": {"type": "noise", "params": {"Scale": 0.625, "Distortion": 2.1, "Detail": 1.948853396000253, "Roughness": 0.8005738209658999}}, "background_texture": {"type": "noise", "params": {"Scale": 0.625, "Distortion": 2.1, "Detail": 1.4865559757754654, "Roughness": 0.8426331590249576}}}, {"image_url": "test_noise/superquadric_3/scale=0.625_distortion=4.000_scene=8", "frame_idx": 2, "probe_touching": true, "probe_location": [243, 373], "gt_bounding_box": [[79, 219], [427, 454]], "mask_idx": 0, "mask_val": 40, "obj_shape_data": [3.125467264526913, 0.8339372028025169, 1.3723045648789318], "obj_scaling_data": [3.0, 3.0, 3.0, 6.0], "obj_shape_type": "supertoroid", "obj_location_data": [1.143983973398774, -1.9026422696706415, -3.3542342003771246], "obj_rotation_data": [0.9950307753654014, 0.0014750603252533983, 0.06078572064623039, -0.07884590311667043], "obj_texture_data": {"type": "noise", "params": {"Scale": 0.625, "Distortion": 4.0, "Detail": 1.3719026818781492, "Roughness": 0.878942371215488}}, "background_texture": {"type": "noise", "params": {"Scale": 0.625, "Distortion": 4.0, "Detail": 1.9461418431047617, "Roughness": 0.550694322326047}}}, {"image_url": "test_noise/superquadric_3/scale=1.000_distortion=0.200_scene=8", "frame_idx": 56, "probe_touching": false, "probe_location": [52, 438], "gt_bounding_box": [], "mask_idx": 0, "mask_val": 0, "obj_shape_data": [1.9481235280353817, 1.653075740831374, 3.889131462650263], "obj_scaling_data": [3.0, 3.0, 3.0, 6.0], "obj_shape_type": "superellipsoid", "obj_location_data": [-8.21347611195963, 0.6727498616639107, -10.920400276498828], "obj_rotation_data": [-0.9396926207859083, 0.0022774048441579356, 0.09438100836323474, 0.3287321358310226], "obj_texture_data": {"type": "noise", "params": {"Scale": 1.0, "Distortion": 0.2, "Detail": 1.5858491494410787, "Roughness": 0.2902565545711926}}, "background_texture": {"type": "noise", "params": {"Scale": 1.0, "Distortion": 0.2, "Detail": 1.0754238729429115, "Roughness": 0.3895806075730491}}}, {"image_url": "test_noise/superquadric_3/scale=1.000_distortion=2.100_scene=8", "frame_idx": 21, "probe_touching": true, "probe_location": [202, 83], "gt_bounding_box": [[0, 0], [313, 249]], "mask_idx": 1, "mask_val": 60, "obj_shape_data": [0.10790684402252901, 0.2789273893815195, 1.9262042798474739], "obj_scaling_data": [3.0, 3.0, 3.0, 6.0], "obj_shape_type": "supertoroid", "obj_location_data": [-9.114050665490472, -1.5563362003853511, 5.594428934283258], "obj_rotation_data": [0.5000000000000001, -0.217246371793409, 0.3104101078532601, 0.7787487264099552], "obj_texture_data": {"type": "noise", "params": {"Scale": 1.0, "Distortion": 2.1, "Detail": 1.723055460735937, "Roughness": 0.42412385116590184}}, "background_texture": {"type": "noise", "params": {"Scale": 1.0, "Distortion": 2.1, "Detail": 1.109231042867687, "Roughness": 0.7945212641522907}}}, {"image_url": "test_noise/superquadric_3/scale=1.000_distortion=4.000_scene=8", "frame_idx": 31, "probe_touching": false, "probe_location": [258, 57], "gt_bounding_box": [], "mask_idx": 0, "mask_val": 0, "obj_shape_data": [3.1357933555475133, 1.1014763862163695, 1.220680997194509], "obj_scaling_data": [3.0, 3.0, 3.0, 6.0], "obj_shape_type": "superellipsoid", "obj_location_data": [-0.2726163523764309, -2.2647737799375225, -2.710232924194476], "obj_rotation_data": [0.024930691738073035, 0.07225997401165267, 0.7954704878566026, -0.6011519439496767], "obj_texture_data": {"type": "noise", "params": {"Scale": 1.0, "Distortion": 4.0, "Detail": 1.173312228016251, "Roughness": 0.38449318080506534}}, "background_texture": {"type": "noise", "params": {"Scale": 1.0, "Distortion": 4.0, "Detail": 1.9067844697016139, "Roughness": 0.2793159791746316}}}, {"image_url": "test_noise/superquadric_4/scale=0.250_distortion=0.200_scene=8", "frame_idx": 21, "probe_touching": true, "probe_location": [157, 292], "gt_bounding_box": [[131, 258], [185, 317]], "mask_idx": 2, "mask_val": 80, "obj_shape_data": [0.4898731656364385, 0.6078855591724306, 3.8016709873374257], "obj_scaling_data": [2.0, 2.0, 2.0, 4.0], "obj_shape_type": "superellipsoid", "obj_location_data": [-11.675318255323157, 0.2025385154117936, -6.413120743953345], "obj_rotation_data": [0.5000000000000001, -0.6876919705513224, -0.3726191267576279, 0.371799327613192], "obj_texture_data": {"type": "noise", "params": {"Scale": 0.25, "Distortion": 0.2, "Detail": 1.6027659488345507, "Roughness": 0.6346559731089307}}, "background_texture": {"type": "noise", "params": {"Scale": 0.25, "Distortion": 0.2, "Detail": 1.156671788033983, "Roughness": 0.7948746154931783}}}, {"image_url": "test_noise/superquadric_4/scale=0.250_distortion=2.100_scene=8", "frame_idx": 17, "probe_touching": false, "probe_location": [441, 429], "gt_bounding_box": [], "mask_idx": 0, "mask_val": 0, "obj_shape_data": [0.41055201605742614, 1.3366541346804994, 0.9584153163446274], "obj_scaling_data": [2.0, 2.0, 2.0, 4.0], "obj_shape_type": "superellipsoid", "obj_location_data": [-2.7106095684617517, -7.649097266562948, 2.6013172887774747], "obj_rotation_data": [0.6616858375968595, -0.4945009461310597, -0.15261103737791118, -0.5425408167775646], "obj_texture_data": {"type": "noise", "params": {"Scale": 0.25, "Distortion": 2.1, "Detail": 1.754327737195727, "Roughness": 0.9329726232499296}}, "background_texture": {"type": "noise", "params": {"Scale": 0.25, "Distortion": 2.1, "Detail": 1.1587273587161802, "Roughness": 0.596440911441286}}}, {"image_url": "test_noise/superquadric_4/scale=0.250_distortion=4.000_scene=8", "frame_idx": 11, "probe_touching": true, "probe_location": [346, 50], "gt_bounding_box": [[158, 0], [450, 231]], "mask_idx": 1, "mask_val": 80, "obj_shape_data": [3.7376194403666476, 1.1659298159168001, 1.7511857111755196], "obj_scaling_data": [2.0, 2.0, 2.0, 4.0], "obj_shape_type": "supertoroid", "obj_location_data": [-13.135742008042822, 10.499230901485088, 4.7598373832962295], "obj_rotation_data": [0.8532908816321556, 0.10625448819479753, -0.05538856917883723, -0.5074807991108642], "obj_texture_data": {"type": "noise", "params": {"Scale": 0.25, "Distortion": 4.0, "Detail": 1.271000771897619, "Roughness": 0.6380581448929058}}, "background_texture": {"type": "noise", "params": {"Scale": 0.25, "Distortion": 4.0, "Detail": 1.9872451472741894, "Roughness": 0.2631442099935335}}}, {"image_url": "test_noise/superquadric_4/scale=0.625_distortion=0.200_scene=8", "frame_idx": 46, "probe_touching": false, "probe_location": [416, 462], "gt_bounding_box": [], "mask_idx": 0, "mask_val": 0, "obj_shape_data": [1.722948361657059, 2.682043427899894, 0.9535783262582251], "obj_scaling_data": [2.0, 2.0, 2.0, 4.0], "obj_shape_type": "supertoroid", "obj_location_data": [-1.4626392981669287, 0.8839769802019297, -8.101115175127294], "obj_rotation_data": [-0.6616858375968595, 0.15731513267719244, 0.32045856439917136, 0.6593406629791021], "obj_texture_data": {"type": "noise", "params": {"Scale": 0.625, "Distortion": 0.2, "Detail": 1.5052835421697985, "Roughness": 0.2552712168363238}}, "background_texture": {"type": "noise", "params": {"Scale": 0.625, "Distortion": 0.2, "Detail": 1.06010294028599, "Roughness": 0.6773245730405153}}}, {"image_url": "test_noise/superquadric_4/scale=0.625_distortion=2.100_scene=8", "frame_idx": 40, "probe_touching": true, "probe_location": [145, 237], "gt_bounding_box": [[37, 176], [189, 267]], "mask_idx": 2, "mask_val": 80, "obj_shape_data": [1.8431764818759735, 2.649138203032995, 2.7259062159697556], "obj_scaling_data": [2.0, 2.0, 2.0, 4.0], "obj_shape_type": "supertoroid", "obj_location_data": [-12.841231295155676, -2.5725879572083343, -1.9222478611151352], "obj_rotation_data": [-0.4112871031306118, -0.6299775734829869, -0.6529939885717162, -0.08700589977765202], "obj_texture_data": {"type": "noise", "params": {"Scale": 0.625, "Distortion": 2.1, "Detail": 1.9693677598689627, "Roughness": 0.5754716661922028}}, "background_texture": {"type": "noise", "params": {"Scale": 0.625, "Distortion": 2.1, "Detail": 1.0251528791668252, "Roughness": 0.4860604512911857}}}, {"image_url": "test_noise/superquadric_4/scale=0.625_distortion=4.000_scene=8", "frame_idx": 50, "probe_touching": false, "probe_location": [230, 100], "gt_bounding_box": [], "mask_idx": 0, "mask_val": 0, "obj_shape_data": [1.392893543077143, 1.9252970452680354, 2.748422978367804], "obj_scaling_data": [2.0, 2.0, 2.0, 4.0], "obj_shape_type": "superellipsoid", "obj_location_data": [3.68185028508206, -4.886370894961283, 1.084557178762822], "obj_rotation_data": [-0.7971325072229225, 0.17215208338868496, -0.4019881597824526, -0.4163519490865272], "obj_texture_data": {"type": "noise", "params": {"Scale": 0.625, "Distortion": 4.0, "Detail": 1.881655940536948, "Roughness": 0.5905522052547192}}, "background_texture": {"type": "noise", "params": {"Scale": 0.625, "Distortion": 4.0, "Detail": 1.675878861520657, "Roughness": 0.2710221475940629}}}, {"image_url": "test_noise/superquadric_4/scale=1.000_distortion=0.200_scene=8", "frame_idx": 22, "probe_touching": true, "probe_location": [146, 350], "gt_bounding_box": [[109, 294], [192, 382]], "mask_idx": 3, "mask_val": 100, "obj_shape_data": [1.468370601667933, 2.1246193676594674, 2.0075255400450125], "obj_scaling_data": [2.0, 2.0, 2.0, 4.0], "obj_shape_type": "superellipsoid", "obj_location_data": [2.3414130996743987, -9.593045132133701, 0.22301407267719664], "obj_rotation_data": [0.4562106573531629, -0.6018472682465862, 0.44362398593882835, 0.48254477607913554], "obj_texture_data": {"type": "noise", "params": {"Scale": 1.0, "Distortion": 0.2, "Detail": 1.1449637406931494, "Roughness": 0.2117471158130796}}, "background_texture": {"type": "noise", "params": {"Scale": 1.0, "Distortion": 0.2, "Detail": 1.5078585311969626, "Roughness": 0.5817902204817975}}}, {"image_url": "test_noise/superquadric_4/scale=1.000_distortion=2.100_scene=8", "frame_idx": 49, "probe_touching": false, "probe_location": [409, 422], "gt_bounding_box": [], "mask_idx": 0, "mask_val": 0, "obj_shape_data": [1.746152743829999, 1.9757244053142888, 0.39276944576597767], "obj_scaling_data": [2.0, 2.0, 2.0, 4.0], "obj_shape_type": "superellipsoid", "obj_location_data": [8.912825637666883, -3.0398320345834935, 5.28397950204892], "obj_rotation_data": [-0.7660444431189779, 0.5826852242332974, 0.24236623076974367, 0.12211654600910717], "obj_texture_data": {"type": "noise", "params": {"Scale": 1.0, "Distortion": 2.1, "Detail": 1.1372073688603481, "Roughness": 0.9747426230211174}}, "background_texture": {"type": "noise", "params": {"Scale": 1.0, "Distortion": 2.1, "Detail": 1.7026910761281453, "Roughness": 0.5716127900385011}}}, {"image_url": "test_noise/superquadric_4/scale=1.000_distortion=4.000_scene=8", "frame_idx": 32, "probe_touching": true, "probe_location": [78, 150], "gt_bounding_box": [[0, 46], [211, 230]], "mask_idx": 3, "mask_val": 100, "obj_shape_data": [2.261456106095951, 2.3077863426418688, 1.4078764471405005], "obj_scaling_data": [2.0, 2.0, 2.0, 4.0], "obj_shape_type": "supertoroid", "obj_location_data": [1.5240119831925802, -10.747855078799189, 7.550201563636515], "obj_rotation_data": [-0.02493069173807269, -0.5236116073974217, 0.7809754534005373, -0.33953893207403285], "obj_texture_data": {"type": "noise", "params": {"Scale": 1.0, "Distortion": 4.0, "Detail": 1.3934422966319708, "Roughness": 0.5892359379588559}}, "background_texture": {"type": "noise", "params": {"Scale": 1.0, "Distortion": 4.0, "Detail": 1.663864662157911, "Roughness": 0.6078042296083932}}}]}